Workbook
Name Adj_prod_LT_Calopeia: Summary!$I$88
Name Adj_prod_LT_Fardo: Summary!$I$91
Name Adj_prod_LT_Sorange: Summary!$I$89
Name Adj_prod_LT_Tyran: Summary!$I$90
Name Avg_demand_per_day_Calopeia: 'Consolidated data'!$B$2
Name Avg_demand_per_day_Entworpe: 'Consolidated data'!$F$2
Name Avg_demand_per_day_Fardo: 'Consolidated data'!$E$2
Name Avg_demand_per_day_Sorange: 'Consolidated data'!$C$2
Name Avg_demand_per_day_Tyran: 'Consolidated data'!$D$2
Name Avg_LT_demand_Calopeia: Summary!$O$88
Name Avg_LT_demand_Fardo: Summary!$O$91
Name Avg_LT_demand_Sorange: Summary!$O$89
Name Avg_LT_demand_Tyran: Summary!$O$90
Name Calopeia_capacity_buffer: Summary!$E$33
Name Capacity_cost: Summary!$D$47
Name Co_Calopeia: Summary!$L$88
Name Co_Fardo: Summary!$L$91
Name Co_Sorange: Summary!$L$89
Name Co_Tyran: Summary!$L$90
Name Cu_Calopeia: Summary!$E$88
Name Cu_Fardo: Summary!$E$91
Name Cu_Sorange: Summary!$E$89
Name Cu_Tyran: Summary!$E$90
Name Cycle_length_Calopeia: Summary!$K$88
Name Cycle_length_Fardo: Summary!$K$91
Name Cycle_length_Sorange: Summary!$K$89
Name Cycle_length_Tyran: Summary!$K$90
Name Effective_LT_Calopeia: Summary!$J$88
Name Effective_LT_Fardo: Summary!$J$91
Name Effective_LT_Sorange: Summary!$J$89
Name Effective_LT_Tyran: Summary!$J$90
Name Factory_cost: Summary!$D$46
Name Fardo_capacity: Summary!$F$55
Name Fardo_capacity_buffer: Summary!$F$33
Name First_phase_demand: Summary!$I$3
Name First_phase_prod_time: Summary!$C$99
Name Forecast_from_day_791_Calopeia: 'Consolidated data'!$H$2
Name Forecast_from_day_791_Entworpe: 'Consolidated data'!$L$2
Name Forecast_from_day_791_Fardo: 'Consolidated data'!$K$2
Name Forecast_from_day_791_Sorange: 'Consolidated data'!$I$2
Name Forecast_from_day_791_Tyran: 'Consolidated data'!$J$2
Name Forecast_from_day_821_Calopeia: 'Consolidated data'!$H$3
Name Forecast_from_day_821_Entworpe: 'Consolidated data'!$L$3
Name Forecast_from_day_821_Fardo: 'Consolidated data'!$K$3
Name Forecast_from_day_821_Sorange: 'Consolidated data'!$I$3
Name Forecast_from_day_821_Tyran: 'Consolidated data'!$J$3
Name Holding_cost: Summary!$C$83
Name Holding_cost_per_drum_day_Calopeia: Summary!$F$88
Name Holding_cost_per_drum_day_Fardo: Summary!$F$91
Name Holding_cost_per_drum_day_Sorange: Summary!$F$89
Name Holding_cost_per_drum_day_Tyran: Summary!$F$90
Name Mailing_cost_continent_Fardo: Summary!$E$43
Name Mailing_cost_different_region: Summary!$E$42
Name Mailing_cost_same_region: Summary!$E$41
Name Original_capacity: Summary!$D$19
Name Practical_batch_Calopeia: Summary!$H$88
Name Practical_batch_Fardo: Summary!$H$91
Name Practical_batch_Sorange: Summary!$H$89
Name Practical_batch_Tyran: Summary!$H$90
Name Production_cost_per_drum_Calopeia: Summary!$D$88

Sheet Summary
D1: Avg. Daily Demand Forecast | M1: Critical rules: All order fulfillment is by mail - cost depends on warehouse-to-customer distance Factory-to-warehouse transport: truck OR mail Truck carries 200 drums, same cost whether full or partial Mail cost per drum: same region $150, continent $200, Fardo $400 Truck cost: same region $15k, continent $20k, Fardo $45k Transit time truck: same region 7 days, continent 7 days, Fardo 14 days Transit time mail: same region 1 day, continent 1 day, Fardo 2 days Order must be shipped within 24 hours or lost - fulfilled from warehouse inventory by mail Production batch cost: $1,500 + $1,000 * drums Holding cost: $100/drum/year whether in warehouse or in transit Interest: 10%/year compounded daily on cash
A2: Phase | B2: From | C2: To | D2: Calopeia | E2: Sorange | F2: Tyran | G2: Fardo | H2: Entworpe | I2: Total/day | J2: Duration | K2: Total/phase
A3: 1st Trough | B3: =731 -> 731 | C3: =B3+72 -> 803 | D3: 16.529495 | E3: 19.6445 | F3: 19.409836 | G3: 15.704918 | H3: 12.5 | I3: =SUM(D3:H3) -> 83.788749 | J3: 73 | K3: =I3*J3 -> 6116.5787
A4: Ramp up | B4: =C3+1 -> 804 | C4: =B4+72 -> 876 | D4: 46.092251 | E4: 30.7916 | F4: 19.409836 | G4: 15.704918 | H4: 12.5 | I4: =SUM(D4:H4) -> 124.4986 | J4: 73 | K4: =I4*J4 -> 9088.3981
A5: Peak | B5: =C4+1 -> 877 | C5: =B5+72 -> 949 | D5: 67.906595 | E5: 41.9387 | F5: 19.409836 | G5: 15.704918 | H5: 12.5 | I5: =SUM(D5:H5) -> 157.46005 | J5: 73 | K5: =I5*J5 -> 11494.584
A6: Decline | B6: =C5+1 -> 950 | C6: =B6+72 -> 1022 | D6: 48.252087 | E6: 53.0858 | F6: 19.409836 | G6: 15.704918 | H6: 12.5 | I6: =SUM(D6:H6) -> 148.95264 | J6: 73 | K6: =I6*J6 -> 10873.543
A7: 2nd Trough | B7: =C6+1 -> 1023 | C7: =B7+72 -> 1095 | D7: 14.329162 | E7: 64.2329 | F7: 19.409836 | G7: 15.704918 | H7: 12.5 | I7: =SUM(D7:H7) -> 126.17682 | J7: 73 | K7: =I7*J7 -> 9210.9076
A8: 1st Trough | B8: =C7+1 -> 1096 | C8: =B8+72 -> 1168 | D8: 16.529495 | E8: 75.38 | F8: 19.409836 | G8: 15.704918 | H8: 12.5 | I8: =SUM(D8:H8) -> 139.52425 | J8: 73 | K8: =I8*J8 -> 10185.27
A9: Ramp up | B9: =C8+1 -> 1169 | C9: =B9+72 -> 1241 | D9: 46.092251 | E9: 86.5271 | F9: 19.409836 | G9: 15.704918 | H9: 12.5 | I9: =SUM(D9:H9) -> 180.2341 | J9: 73 | K9: =I9*J9 -> 13157.09
A10: Peak | B10: =C9+1 -> 1242 | C10: =B10+72 -> 1314 | D10: 67.906595 | E10: 97.6742 | F10: 19.409836 | G10: 15.704918 | H10: 12.5 | I10: =SUM(D10:H10) -> 213.19555 | J10: 73 | K10: =I10*J10 -> 15563.275
A11: Decline | B11: =C10+1 -> 1315 | C11: =B11+72 -> 1387 | D11: 48.252087 | E11: 108.8213 | F11: 19.409836 | G11: 15.704918 | H11: 12.5 | I11: =SUM(D11:H11) -> 204.68814 | J11: 73 | K11: =I11*J11 -> 14942.234
A12: 2nd Trough | B12: =C11+1 -> 1388 | C12: =B12+41 -> 1429 | D12: 14.329162 | E12: 117.60155 | F12: 19.409836 | G12: 15.704918 | H12: 12.5 | I12: =SUM(D12:H12) -> 179.54547 | J12: 42 | K12: =I12*J12 -> 7540.9096
A13: From day 1430 | B13: =C12+1 -> 1430 | C13: =B13+30 -> 1460 | D13: 7.1645811 | E13: 61.18035 | F13: 9.704918 | G13: 7.852459 | H13: 6.25 | I13: =SUM(D13:H13) -> 92.152308 | J13: 31 | K13: =I13*J13 -> 2856.7216
H14: TOTAL | I14: =SUM(I3:I13) -> 1650.2167 | J14: =SUM(J3:J13) -> 730 | K14: =SUM(K3:K13) -> 111029.51
A17: 1. Minimum capacity from total demand | D17: =K14/J14 -> 152.09522
A18: 2. Account for 90-day build period
B19: Original capacity | D19: 70
B20: Starting inventory (at day 730) | D20: 2528
B21: Production | D21: =90*Original_capacity -> 6300
B22: Demand | D22: =K3+I4*17 -> 8233.055
B23: Remaining inventory (at day 821) | D23: =Starting_Inventory+D21-D22 -> 594.94503
A25: 3. Minimum capacity needed after day 820
D26: without Fardo factory | E26: with Fardo factory | F26: Fardo factory
B27: Remaining demand | D27: =K14-D22 -> 102796.46 | E27: =D27-Forecast_from_day_821_Fardo -> 93232.161 | F27: =Forecast_from_day_821_Fardo -> 9564.2951
B28: Factory build/Capacity expansion time (days) | D28: 90
B29: Remaining time +1 factory/capacity | D29: =1430 - (730+90) -> 610
B30: Warehouse build time | D30: 60
B31: Remaining time +1 warehouse | D31: =1430-(730+60) -> 640
B32: Min capacity | D32: =D27/Remaining_time_factory_capacity -> 168.51878 | E32: =E27/Remaining_time_factory_capacity -> 152.83961 | F32: =F27/Remaining_time_factory_capacity -> 15.679172
B33: Safety buffer (10%) | D33: =D32*1.1 -> 185.37066 | E33: =E32*1.1 -> 168.12357 | F33: =F32*1.1 -> 17.247089
A35: 4. Transportation costs & times
B36: Always use truck for factory-to-warehouse transport.
B37: All orders fulfilled by mail. Warehouse must ship within 24 hours of order receipt or sale permanently lost ==> must have stock on hand
D39: cost | F39: time (days)
D40: truck$/drum (batch of 200) | E40: mail$/drum | F40: truck | G40: mail
B41: Same region | D41: =15000/200 -> 75 | E41: 150 | F41: 7 | G41: 1
B42: Different regions on continent | D42: =20000/200 -> 100 | E42: 200 | F42: 7 | G42: 1
B43: Between continent and Fardo | D43: =45000/200 -> 225 | E43: 400 | F43: 14 | G43: 2
A45: 5. New factory + warehouse decision
B46: +1 factory cost | D46: 500000
B47: +1 capacity cost | D47: 50000
B48: +1 warehouse cost | D48: 100000
B50: Transport savings & Breakeven
B51: Location | C51: From Calopeia | D51: From local | E51: Saving/drum | F51: Min capacity after day 820 | G51: Total cost | H51: Breakeven | I51: Forecast | J51: Net gain | K51: Decision
B52: Sorange | C52: =Trucking_cost_same_region+Mailing_cost_different_region -> 275 | D52: =Trucking_cost_same_region+Mailing_cost_same_region -> 225 | E52: =C52-D52 -> 50 | F52: =Forecast_from_day_821_Sorange/Remaining_time_factory_capacity -> 74.165842 | G52: =Factory_cost+Capacity_cost*F52+WH_cost -> 4308292.1 | H52: =G52/E52 -> 86165.842 | I52: =Forecast_from_day_821_Sorange -> 45241.164 | J52: =(I52-H52)*E52 -> -2046233.9 | K52: Skip
B53: Tyran | C53: =Trucking_cost_same_region+Mailing_cost_different_region -> 275 | D53: =Trucking_cost_same_region+Mailing_cost_same_region -> 225 | E53: =C53-D53 -> 50 | F53: =Forecast_from_day_821_Tyran/Remaining_time_factory_capacity -> 19.378017 | G53: =Factory_cost+Capacity_cost*F53+WH_cost -> 1568900.8 | H53: =G53/E53 -> 31378.017 | I53: =Forecast_from_day_821_Tyran -> 11820.59 | J53: =(I53-H53)*E53 -> -977871.32 | K53: Skip
B54: Entworpe | C54: =Trucking_cost_same_region+Mailing_cost_different_region -> 275 | D54: =Trucking_cost_same_region+Mailing_cost_same_region -> 225 | E54: =C54-D54 -> 50 | F54: =Forecast_from_day_821_Entworpe/Remaining_time_factory_capacity -> 12.479508 | G54: =Factory_cost+Capacity_cost*F54+WH_cost -> 1223975.4 | H54: =G54/E54 -> 24479.508 | I54: =Forecast_from_day_821_Entworpe -> 7612.5 | J54: =(I54-H54)*E54 -> -843350.41 | K54: Skip
B55: Fardo | C55: =Trucking_cost_same_region+Mailing_cost_continent_Fardo -> 475 | D55: =Trucking_cost_same_region+Mailing_cost_same_region -> 225 | E55: =C55-D55 -> 250 | F55: =Forecast_from_day_821_Fardo/Remaining_time_factory_capacity -> 15.679172 | G55: =Factory_cost+Capacity_cost*F55+WH_cost -> 1383958.6 | H55: =G55/E55 -> 5535.8345 | I55: =Forecast_from_day_821_Fardo -> 9564.2951 | J55: =(I55-H55)*E55 -> 1007115.2 | K55: Further check
A57: 6. New warehouse only decision
B59: Transport savings & Breakeven
B60: Location | C60: From Calopeia | D60: From local | E60: Saving/drum | F60: Breakeven | G60: Forecast | H60: Net gain | I60: Decision
B61: Sorange | C61: =Trucking_cost_same_region+Mailing_cost_different_region -> 275 | D61: =Trucking_cost_different_region+Mailing_cost_same_region -> 250 | E61: =C61-D61 -> 25 | F61: =WH_cost/E61 -> 4000 | G61: =Forecast_from_day_791_Sorange -> 46006.626 | H61: =(G61-F61)*E61 -> 1050165.7 | I61: WH only
B62: Tyran | C62: =Trucking_cost_same_region+Mailing_cost_different_region -> 275 | D62: =Trucking_cost_different_region+Mailing_cost_same_region -> 250 | E62: =C62-D62 -> 25 | F62: =WH_cost/E62 -> 4000 | G62: =Forecast_from_day_791_Tyran -> 12402.885 | H62: =(G62-F62)*E62 -> 210072.13 | I62: WH only
B63: Entworpe | C63: =Trucking_cost_same_region+Mailing_cost_different_region -> 275 | D63: =Trucking_cost_different_region+Mailing_cost_same_region -> 250 | E63: =C63-D63 -> 25 | F63: =WH_cost/E63 -> 4000 | G63: =Forecast_from_day_791_Entworpe -> 7987.5 | H63: =(G63-F63)*E63 -> 99687.5 | I63: Skip
B64: Fardo | C64: =Trucking_cost_same_region+Mailing_cost_continent_Fardo -> 475 | D64: =Trucking_cost_continent_Fardo+Mailing_cost_same_region -> 375 | E64: =C64-D64 -> 100 | F64: =WH_cost/E64 -> 1000 | G64: =Forecast_from_day_791_Fardo -> 10035.443 | H64: =(G64-F64)*E64 -> 903544.26 | I64: Factory + WH beats
A66: 7. Supply chain network structure
B67: All fulfillment is by mail within 24 hours of order receipt. Factories ship to warehouses by truck.
B68: Factory | C68: to WH | D68: fulfills | E68: period
B69: Calopeia | C69: Calopeia | D69: all 5 regions | E69: Day 730 - 790
B70: Calopeia | C70: Calopeia | D70: Calopeia, Entworpe, Fardo | E70: Day 790 - 820
C71: Sorange | D71: Sorange
C72: Tyran | D72: Tyran
B73: Calopeia | C73: Calopeia | D73: Calopeia, Entworpe | E73: Day 820 onward
C74: Sorange | D74: Sorange
C75: Tyran | D75: Tyran
B76: Fardo | C76: Fardo | D76: Fardo
A78: 8. Reorder Point (ROP) from day 820 onward
B79: Key parameters
B80: Revenue per drum | C80: 1450
B81: Variable production cost | C81: 1000 | D81: per drum
B82: Setup cost per batch | C82: 1500 | D82: per production run regardless of size
B83: Holding cost | C83: 100 | D83: per drum per year; whether in warehouse or in transit
B84: Interest rate | C84: 0.1 | D84: opportunity cost of cash tied up in inventory
B85: Truck capacity | C85: 200 | D85: same cost whether full or partial
B87: Factory | C87: to WH | D87: Production cost/drum | E87: Profit margin/drum | F87: Holding cost/drum/day | G87: EOQ | H87: Practical batch | I87: Adjusted production lead time | J87: Effective LT | K87: Cycle length | L87: Overage cost per cycle | M87: Target service level | N87: z-score | O87: Avg. LT demand | P87: Safety Stock | Q87: ROP
B88: Calopeia | C88: Calopeia | D88: =Setup_cost_per_batch/Practical_batch_Calopeia+Variable_production_cost -> 1007.5 | E88: =Revenue_per_drum-Production_cost_per_drum_Calopeia-Trucking_cost_same_region-Mailing_cost_same_region -> 217.5 | F88: =(Holding_cost+(Production_cost_per_drum_Calopeia+Trucking_cost_same_region)*0.1)/365 -> 0.57054795 | G88: =SQRT(2 * (Avg_demand_per_day_Calopeia + Avg_demand_per_day_Entworpe) * Setup_cost_per_batch / Holding_cost_per_drum_day_Calopeia) -> 533.59636 | H88: 200 | I88: =Practical_batch_Calopeia/Calopeia_capacity_buffer+Practical_batch_Sorange/Calopeia_capacity_buffer+Practical_batch_Tyran/Calopeia_capacity_buffer -> 5.948006 | J88: =Adj_prod_LT_Calopeia+Truck_time_same_region -> 12.948006 | K88: =Practical_batch_Calopeia/(Avg_demand_per_day_Calopeia+Avg_demand_per_day_Entworpe) -> 3.6934599 | L88: =Holding_cost_per_drum_day_Calopeia*Cycle_length_Calopeia -> 2.1072959 | M88: =Cu_Calopeia/(Cu_Calopeia+Co_Calopeia) -> 0.99040425 | N88: =NORMSINV(SL_Calopeia) -> 2.3417903 | O88: =(Avg_demand_per_day_Calopeia+Avg_demand_per_day_Entworpe)*Effective_LT_Calopeia -> 701.13154 | P88: =std_Calopeia_WH*z_Calopeia*SQRT(Effective_LT_Calopeia) -> 470.02827 | Q88: =Avg_LT_demand_Calopeia+SS_Calopeia -> 1171.1598
C89: Sorange | D89: =Setup_cost_per_batch/Practical_batch_Sorange+Variable_production_cost -> 1003.75 | E89: =Revenue_per_drum-Production_cost_per_drum_Sorange-Trucking_cost_different_region-Mailing_cost_different_region -> 146.25 | F89: =(Holding_cost+(Production_cost_per_drum_Sorange+Trucking_cost_different_region)*0.1)/365 -> 0.57636986 | G89: =SQRT(2 * Avg_demand_per_day_Sorange * Setup_cost_per_batch / Holding_cost_per_drum_day_Sorange) -> 621.82508 | H89: 400 | I89: =Practical_batch_Calopeia/Calopeia_capacity_buffer+Practical_batch_Sorange/Calopeia_capacity_buffer+Practical_batch_Tyran/Calopeia_capacity_buffer -> 5.948006 | J89: =Adj_prod_LT_Sorange+Truck_time_different_region -> 12.948006 | K89: =Practical_batch_Sorange/Avg_demand_per_day_Sorange -> 5.3844769 | L89: =Holding_cost_per_drum_day_Sorange*Cycle_length_Sorange -> 3.1034502 | M89: =Cu_Sorange/(Cu_Sorange+Co_Sorange) -> 0.97922077 | N89: =NORMSINV(SL_Sorange) -> 2.0379147 | O89: =Avg_demand_per_day_Sorange*Effective_LT_Sorange -> 961.87662 | P89: =std_Sorange*z_Sorange*SQRT(Effective_LT_Sorange) -> 66.680892 | Q89: =Avg_LT_demand_Sorange+SS_Sorange -> 1028.5575
C90: Tyran | D90: =Setup_cost_per_batch/Practical_batch_Tyran+Variable_production_cost -> 1003.75 | E90: =Revenue_per_drum-Production_cost_per_drum_Tyran-Trucking_cost_different_region-Mailing_cost_different_region -> 146.25 | F90: =(Holding_cost+(Production_cost_per_drum_Tyran+Trucking_cost_different_region)*0.1)/365 -> 0.57636986 | G90: =SQRT(2 * Avg_demand_per_day_Tyran * Setup_cost_per_batch / Holding_cost_per_drum_day_Tyran) -> 317.84906 | H90: 400 | I90: =Practical_batch_Calopeia/Calopeia_capacity_buffer+Practical_batch_Sorange/Calopeia_capacity_buffer+Practical_batch_Tyran/Calopeia_capacity_buffer -> 5.948006 | J90: =Adj_prod_LT_Tyran+Truck_time_different_region -> 12.948006 | K90: =Practical_batch_Tyran/Avg_demand_per_day_Tyran -> 20.608108 | L90: =Holding_cost_per_drum_day_Tyran*Cycle_length_Tyran -> 11.877892 | M90: =Cu_Tyran/(Cu_Tyran+Co_Tyran) -> 0.92488427 | N90: =NORMSINV(SL_Tyran) -> 1.4387144 | O90: =Avg_demand_per_day_Tyran*Effective_LT_Tyran -> 251.31867 | P90: =std_Tyran*z_Tyran*SQRT(Effective_LT_Tyran) -> 87.496368 | Q90: =Avg_LT_demand_Tyran+SS_Tyran -> 338.81504
B91: Fardo | C91: Fardo | D91: =Setup_cost_per_batch/Practical_batch_Fardo+Variable_production_cost -> 1003.75 | E91: =Revenue_per_drum-Production_cost_per_drum_Fardo-Trucking_cost_same_region-Mailing_cost_same_region -> 221.25 | F91: =(Holding_cost+(Production_cost_per_drum_Fardo+Trucking_cost_same_region)*0.1)/365 -> 0.56952055 | G91: =SQRT(2 * Avg_demand_per_day_Fardo * Setup_cost_per_batch / Holding_cost_per_drum_day_Fardo) -> 287.6231 | H91: 400 | I91: =Practical_batch_Fardo/Fardo_capacity -> 25.511551 | J91: =Adj_prod_LT_Fardo+Truck_time_same_region -> 32.511551 | K91: =Practical_batch_Fardo/Avg_demand_per_day_Fardo -> 25.469729 | L91: =Holding_cost_per_drum_day_Fardo*Cycle_length_Fardo -> 14.505534 | M91: =Cu_Fardo/(Cu_Fardo+Co_Fardo) -> 0.93847214 | N91: =NORMSINV(SL_Fardo) -> 1.5420735 | O91: =Avg_demand_per_day_Fardo*Effective_LT_Fardo -> 510.59124 | P91: =std_Fardo*z_Fardo*SQRT(Effective_LT_Fardo) -> 147.51843 | Q91: =Avg_LT_demand_Fardo+SS_Fardo -> 658.10967
A93: 9. Cash Flow Feasibility
B94: Starting-cash balance (at day 730) | C94: 6797000
B95: Expand the Calopeia | C95: =(Calopeia_capacity_buffer-Original_capacity)*Capacity_cost -> 4906178.4
B96: Build the Fardo factory + capacity + warehouse | C96: =Fardo_capacity_buffer*Capacity_cost+Factory_cost+WH_cost -> 1462354.5
B97: Build Sorange & Tyran warehouses | C97: =WH_cost*2 -> 200000
B98: Remaining working capital | C98: =C94-SUM(C95:C97) -> 228467.08
A100: 10. End-of-life wind-down
B101: All regions: linear decay from day 1430 to day 1460
B102: Both factories: stop at day 1445
B103: Any drum produced after day 1445 arrives with near-zero demand - risks stranding at $1,000/drum variable cost, $0 value at day 1460
B105: Day | C105: Action
B106: 1430 | C106: Reduce all ROPs by 50%
B107: 1445 | C107: Stop all production at both factories
B108: 1460 | C108: Game ends

Sheet Consolidated data
B1: average & std of demand | H1: forecasted demand | M1: combined route: Calopeia + Entworpe
A2: AVERAGE after day 90 (or day 820 in forecast) | B2: =AVERAGE(B95:B734) -> 41.854687 | C2: =AVERAGE(I95:I703) -> 74.287625 | D2: =AVERAGE(D674:D734) -> 19.409836 | E2: =AVERAGE(E674:E734) -> 15.704918 | F2: =AVERAGE(F674:F734) -> 12.295082 | G2: Day 791 - 1429 | H2: =SUM(H65:H703) -> 26758.026 | I2: =SUM(I65:I703) -> 46006.626 | J2: =SUM(J65:J703) -> 12402.885 | K2: =SUM(K65:K703) -> 10035.443 | L2: =SUM(L65:L703) -> 7987.5 | M2: std
A3: STDEV after day 90 (or day 820 in forecast) | B3: =STDEV(B5:B734) -> 26.51127 | C3: =STDEV(C644:C734) -> 9.0931417 | D3: =STDEV(D674:D734) -> 16.901062 | E3: =STDEV(E674:E734) -> 16.77731 | F3: =STDEV(F674:F734) -> 54.509737 | G3: Day 821 - 1429 | H3: =SUM(H95:H703) -> 25759.575 | I3: =SUM(I95:I703) -> 45241.164 | J3: =SUM(J95:J703) -> 11820.59 | K3: =SUM(K95:K703) -> 9564.2951 | L3: =SUM(L95:L703) -> 7612.5 | M3: =STDEV(M674:M734) -> 55.779489
A4: historical - day | B4: Calopeia | C4: Sorange | D4: Tyran | E4: Fardo | F4: Entworpe | G4: forecast - day | H4: Calopeia | I4: Sorange | J4: Tyran | K4: Fardo | L4: Entworpe | M4: Calopeia + Entworpe
A5: 1 | B5: =Calopeia!B2 -> 11 | C5: =Sorange!B2 -> 0 | D5: =Tyran!B2 -> 0 | E5: =Fardo!B2 -> 0 | F5: =Entworpe!B2 -> 0 | G5: 731 | H5: =Calopeia!F2 -> 16.529495 | I5: =Sorange!E2 -> 14.142857 | J5: =Tyran!D2 -> 19.409836 | K5: =Fardo!D2 -> 15.704918 | L5: =Entworpe!D2 -> 12.5 | M5: =B5+F5 -> 11
A6: 2 | B6: =Calopeia!B3 -> 7 | C6: =Sorange!B3 -> 0 | D6: =Tyran!B3 -> 0 | E6: =Fardo!B3 -> 0 | F6: =Entworpe!B3 -> 0 | G6: 732 | H6: =Calopeia!F3 -> 16.529495 | I6: =Sorange!E3 -> 14.295509 | J6: =Tyran!D3 -> 19.409836 | K6: =Fardo!D3 -> 15.704918 | L6: =Entworpe!D3 -> 12.5 | M6: =B6+F6 -> 7
A7: 3 | B7: =Calopeia!B4 -> 4 | C7: =Sorange!B4 -> 0 | D7: =Tyran!B4 -> 0 | E7: =Fardo!B4 -> 0 | F7: =Entworpe!B4 -> 0 | G7: 733 | H7: =Calopeia!F4 -> 16.529495 | I7: =Sorange!E4 -> 14.448161 | J7: =Tyran!D4 -> 19.409836 | K7: =Fardo!D4 -> 15.704918 | L7: =Entworpe!D4 -> 12.5 | M7: =B7+F7 -> 4
A8: 4 | B8: =Calopeia!B5 -> 8 | C8: =Sorange!B5 -> 0 | D8: =Tyran!B5 -> 0 | E8: =Fardo!B5 -> 0 | F8: =Entworpe!B5 -> 0 | G8: 734 | H8: =Calopeia!F5 -> 16.529495 | I8: =Sorange!E5 -> 14.600812 | J8: =Tyran!D5 -> 19.409836 | K8: =Fardo!D5 -> 15.704918 | L8: =Entworpe!D5 -> 12.5 | M8: =B8+F8 -> 8
A9: 5 | B9: =Calopeia!B6 -> 5 | C9: =Sorange!B6 -> 0 | D9: =Tyran!B6 -> 0 | E9: =Fardo!B6 -> 0 | F9: =Entworpe!B6 -> 0 | G9: 735 | H9: =Calopeia!F6 -> 16.529495 | I9: =Sorange!E6 -> 14.753464 | J9: =Tyran!D6 -> 19.409836 | K9: =Fardo!D6 -> 15.704918 | L9: =Entworpe!D6 -> 12.5 | M9: =B9+F9 -> 5
A10: 6 | B10: =Calopeia!B7 -> 8 | C10: =Sorange!B7 -> 0 | D10: =Tyran!B7 -> 0 | E10: =Fardo!B7 -> 0 | F10: =Entworpe!B7 -> 0 | G10: 736 | H10: =Calopeia!F7 -> 16.529495 | I10: =Sorange!E7 -> 14.906116 | J10: =Tyran!D7 -> 19.409836 | K10: =Fardo!D7 -> 15.704918 | L10: =Entworpe!D7 -> 12.5 | M10: =B10+F10 -> 8
A11: 7 | B11: =Calopeia!B8 -> 14 | C11: =Sorange!B8 -> 0 | D11: =Tyran!B8 -> 0 | E11: =Fardo!B8 -> 0 | F11: =Entworpe!B8 -> 0 | G11: 737 | H11: =Calopeia!F8 -> 16.529495 | I11: =Sorange!E8 -> 15.058767 | J11: =Tyran!D8 -> 19.409836 | K11: =Fardo!D8 -> 15.704918 | L11: =Entworpe!D8 -> 12.5 | M11: =B11+F11 -> 14
A12: 8 | B12: =Calopeia!B9 -> 6 | C12: =Sorange!B9 -> 0 | D12: =Tyran!B9 -> 0 | E12: =Fardo!B9 -> 0 | F12: =Entworpe!B9 -> 0 | G12: 738 | H12: =Calopeia!F9 -> 16.529495 | I12: =Sorange!E9 -> 15.211419 | J12: =Tyran!D9 -> 19.409836 | K12: =Fardo!D9 -> 15.704918 | L12: =Entworpe!D9 -> 12.5 | M12: =B12+F12 -> 6
A13: 9 | B13: =Calopeia!B10 -> 31 | C13: =Sorange!B10 -> 0 | D13: =Tyran!B10 -> 0 | E13: =Fardo!B10 -> 0 | F13: =Entworpe!B10 -> 0 | G13: 739 | H13: =Calopeia!F10 -> 16.529495 | I13: =Sorange!E10 -> 15.364071 | J13: =Tyran!D10 -> 19.409836 | K13: =Fardo!D10 -> 15.704918 | L13: =Entworpe!D10 -> 12.5 | M13: =B13+F13 -> 31
A14: 10 | B14: =Calopeia!B11 -> 7 | C14: =Sorange!B11 -> 0 | D14: =Tyran!B11 -> 0 | E14: =Fardo!B11 -> 0 | F14: =Entworpe!B11 -> 0 | G14: 740 | H14: =Calopeia!F11 -> 16.529495 | I14: =Sorange!E11 -> 15.516722 | J14: =Tyran!D11 -> 19.409836 | K14: =Fardo!D11 -> 15.704918 | L14: =Entworpe!D11 -> 12.5 | M14: =B14+F14 -> 7
A15: 11 | B15: =Calopeia!B12 -> 7 | C15: =Sorange!B12 -> 0 | D15: =Tyran!B12 -> 0 | E15: =Fardo!B12 -> 0 | F15: =Entworpe!B12 -> 0 | G15: 741 | H15: =Calopeia!F12 -> 16.529495 | I15: =Sorange!E12 -> 15.669374 | J15: =Tyran!D12 -> 19.409836 | K15: =Fardo!D12 -> 15.704918 | L15: =Entworpe!D12 -> 12.5 | M15: =B15+F15 -> 7
A16: 12 | B16: =Calopeia!B13 -> 19 | C16: =Sorange!B13 -> 0 | D16: =Tyran!B13 -> 0 | E16: =Fardo!B13 -> 0 | F16: =Entworpe!B13 -> 0 | G16: 742 | H16: =Calopeia!F13 -> 16.529495 | I16: =Sorange!E13 -> 15.822026 | J16: =Tyran!D13 -> 19.409836 | K16: =Fardo!D13 -> 15.704918 | L16: =Entworpe!D13 -> 12.5 | M16: =B16+F16 -> 19
... A369: 365 | B369: =Calopeia!B366 -> 14 | C369: =Sorange!B366 -> 0 | D369: =Tyran!B366 -> 0 | E369: =Fardo!B366 -> 0 | F369: =Entworpe!B366 -> 0 | G369: 1095 | H369: =Calopeia!F366 -> 14.329162 | I369: =Sorange!E366 -> 69.708075 | J369: =Tyran!D366 -> 19.409836 | K369: =Fardo!D366 -> 15.704918 | L369: =Entworpe!D366 -> 12.5 | M369: =B369+F369 -> 14
A370: 366 | B370: =Calopeia!D2 -> 5 | C370: =Sorange!B367 -> 0 | D370: =Tyran!B367 -> 0 | E370: =Fardo!B367 -> 0 | F370: =Entworpe!B367 -> 0 | G370: 1096 | H370: =Calopeia!H2 -> 16.529495 | I370: =Sorange!E367 -> 69.860726 | J370: =Tyran!D367 -> 19.409836 | K370: =Fardo!D367 -> 15.704918 | L370: =Entworpe!D367 -> 12.5 | M370: =B370+F370 -> 5
A371: 367 | B371: =Calopeia!D3 -> 4 | C371: =Sorange!B368 -> 0 | D371: =Tyran!B368 -> 0 | E371: =Fardo!B368 -> 0 | F371: =Entworpe!B368 -> 0 | G371: 1097 | H371: =Calopeia!H3 -> 16.529495 | I371: =Sorange!E368 -> 70.013378 | J371: =Tyran!D368 -> 19.409836 | K371: =Fardo!D368 -> 15.704918 | L371: =Entworpe!D368 -> 12.5 | M371: =B371+F371 -> 4
A372: 368 | B372: =Calopeia!D4 -> 9 | C372: =Sorange!B369 -> 0 | D372: =Tyran!B369 -> 0 | E372: =Fardo!B369 -> 0 | F372: =Entworpe!B369 -> 0 | G372: 1098 | H372: =Calopeia!H4 -> 16.529495 | I372: =Sorange!E369 -> 70.16603 | J372: =Tyran!D369 -> 19.409836 | K372: =Fardo!D369 -> 15.704918 | L372: =Entworpe!D369 -> 12.5 | M372: =B372+F372 -> 9
A373: 369 | B373: =Calopeia!D5 -> 9 | C373: =Sorange!B370 -> 0 | D373: =Tyran!B370 -> 0 | E373: =Fardo!B370 -> 0 | F373: =Entworpe!B370 -> 0 | G373: 1099 | H373: =Calopeia!H5 -> 16.529495 | I373: =Sorange!E370 -> 70.318681 | J373: =Tyran!D370 -> 19.409836 | K373: =Fardo!D370 -> 15.704918 | L373: =Entworpe!D370 -> 12.5 | M373: =B373+F373 -> 9
A374: 370 | B374: =Calopeia!D6 -> 1 | C374: =Sorange!B371 -> 0 | D374: =Tyran!B371 -> 0 | E374: =Fardo!B371 -> 0 | F374: =Entworpe!B371 -> 0 | G374: 1100 | H374: =Calopeia!H6 -> 16.529495 | I374: =Sorange!E371 -> 70.471333 | J374: =Tyran!D371 -> 19.409836 | K374: =Fardo!D371 -> 15.704918 | L374: =Entworpe!D371 -> 12.5 | M374: =B374+F374 -> 1
A375: 371 | B375: =Calopeia!D7 -> 29 | C375: =Sorange!B372 -> 0 | D375: =Tyran!B372 -> 0 | E375: =Fardo!B372 -> 0 | F375: =Entworpe!B372 -> 0 | G375: 1101 | H375: =Calopeia!H7 -> 16.529495 | I375: =Sorange!E372 -> 70.623985 | J375: =Tyran!D372 -> 19.409836 | K375: =Fardo!D372 -> 15.704918 | L375: =Entworpe!D372 -> 12.5 | M375: =B375+F375 -> 29
A376: 372 | B376: =Calopeia!D8 -> 6 | C376: =Sorange!B373 -> 0 | D376: =Tyran!B373 -> 0 | E376: =Fardo!B373 -> 0 | F376: =Entworpe!B373 -> 0 | G376: 1102 | H376: =Calopeia!H8 -> 16.529495 | I376: =Sorange!E373 -> 70.776636 | J376: =Tyran!D373 -> 19.409836 | K376: =Fardo!D373 -> 15.704918 | L376: =Entworpe!D373 -> 12.5 | M376: =B376+F376 -> 6
A377: 373 | B377: =Calopeia!D9 -> 4 | C377: =Sorange!B374 -> 0 | D377: =Tyran!B374 -> 0 | E377: =Fardo!B374 -> 0 | F377: =Entworpe!B374 -> 0 | G377: 1103 | H377: =Calopeia!H9 -> 16.529495 | I377: =Sorange!E374 -> 70.929288 | J377: =Tyran!D374 -> 19.409836 | K377: =Fardo!D374 -> 15.704918 | L377: =Entworpe!D374 -> 12.5 | M377: =B377+F377 -> 4
A378: 374 | B378: =Calopeia!D10 -> 1 | C378: =Sorange!B375 -> 0 | D378: =Tyran!B375 -> 0 | E378: =Fardo!B375 -> 0 | F378: =Entworpe!B375 -> 0 | G378: 1104 | H378: =Calopeia!H10 -> 16.529495 | I378: =Sorange!E375 -> 71.08194 | J378: =Tyran!D375 -> 19.409836 | K378: =Fardo!D375 -> 15.704918 | L378: =Entworpe!D375 -> 12.5 | M378: =B378+F378 -> 1
A379: 375 | B379: =Calopeia!D11 -> 13 | C379: =Sorange!B376 -> 0 | D379: =Tyran!B376 -> 0 | E379: =Fardo!B376 -> 0 | F379: =Entworpe!B376 -> 0 | G379: 1105 | H379: =Calopeia!H11 -> 16.529495 | I379: =Sorange!E376 -> 71.234591 | J379: =Tyran!D376 -> 19.409836 | K379: =Fardo!D376 -> 15.704918 | L379: =Entworpe!D376 -> 12.5 | M379: =B379+F379 -> 13
A380: 376 | B380: =Calopeia!D12 -> 2 | C380: =Sorange!B377 -> 0 | D380: =Tyran!B377 -> 0 | E380: =Fardo!B377 -> 0 | F380: =Entworpe!B377 -> 0 | G380: 1106 | H380: =Calopeia!H12 -> 16.529495 | I380: =Sorange!E377 -> 71.387243 | J380: =Tyran!D377 -> 19.409836 | K380: =Fardo!D377 -> 15.704918 | L380: =Entworpe!D377 -> 12.5 | M380: =B380+F380 -> 2
A381: 377 | B381: =Calopeia!D13 -> 2 | C381: =Sorange!B378 -> 0 | D381: =Tyran!B378 -> 0 | E381: =Fardo!B378 -> 0 | F381: =Entworpe!B378 -> 0 | G381: 1107 | H381: =Calopeia!H13 -> 16.529495 | I381: =Sorange!E378 -> 71.539895 | J381: =Tyran!D378 -> 19.409836 | K381: =Fardo!D378 -> 15.704918 | L381: =Entworpe!D378 -> 12.5 | M381: =B381+F381 -> 2
... A703: 699 | B703: =Calopeia!D335 -> 10 | C703: =Sorange!B700 -> 8 | D703: =Tyran!B700 -> 9 | E703: =Fardo!B700 -> 0 | F703: =Entworpe!B700 -> 0 | G703: 1429 | H703: =Calopeia!H335 -> 14.329162 | I703: =Sorange!E700 -> 120.69374 | J703: =Tyran!D700 -> 19.409836 | K703: =Fardo!D700 -> 15.704918 | L703: =Entworpe!D700 -> 12.5 | M703: =B703+F703 -> 10
A704: 700 | B704: =Calopeia!D336 -> 12 | C704: =Sorange!B701 -> 18 | D704: =Tyran!B701 -> 47 | E704: =Fardo!B701 -> 1 | F704: =Entworpe!B701 -> 250 | G704: 1430 | H704: =Calopeia!I336 -> 14.329162 | I704: =Sorange!F701 -> 120.84639 | J704: =Tyran!E701 -> 19.409836 | K704: =Fardo!E701 -> 15.704918 | L704: =Entworpe!E701 -> 12.5 | M704: =B704+F704 -> 262
A705: 701 | B705: =Calopeia!D337 -> 3 | C705: =Sorange!B702 -> 2 | D705: =Tyran!B702 -> 0 | E705: =Fardo!B702 -> 26 | F705: =Entworpe!B702 -> 0 | G705: 1431 | H705: =Calopeia!I337 -> 13.851523 | I705: =Sorange!F702 -> 116.96574 | J705: =Tyran!E702 -> 18.762842 | K705: =Fardo!E702 -> 15.181421 | L705: =Entworpe!E702 -> 12.083333 | M705: =B705+F705 -> 3
A706: 702 | B706: =Calopeia!D338 -> 38 | C706: =Sorange!B703 -> 11 | D706: =Tyran!B703 -> 0 | E706: =Fardo!B703 -> 4 | F706: =Entworpe!B703 -> 0 | G706: 1432 | H706: =Calopeia!I338 -> 13.373885 | I706: =Sorange!F703 -> 113.07492 | J706: =Tyran!E703 -> 18.115847 | K706: =Fardo!E703 -> 14.657923 | L706: =Entworpe!E703 -> 11.666667 | M706: =B706+F706 -> 38
A707: 703 | B707: =Calopeia!D339 -> 11 | C707: =Sorange!B704 -> 3 | D707: =Tyran!B704 -> 10 | E707: =Fardo!B704 -> 35 | F707: =Entworpe!B704 -> 0 | G707: 1433 | H707: =Calopeia!I339 -> 12.896246 | I707: =Sorange!F704 -> 109.17391 | J707: =Tyran!E704 -> 17.468852 | K707: =Fardo!E704 -> 14.134426 | L707: =Entworpe!E704 -> 11.25 | M707: =B707+F707 -> 11
A708: 704 | B708: =Calopeia!D340 -> 13 | C708: =Sorange!B705 -> 4 | D708: =Tyran!B705 -> 24 | E708: =Fardo!B705 -> 6 | F708: =Entworpe!B705 -> 0 | G708: 1434 | H708: =Calopeia!I340 -> 12.418607 | I708: =Sorange!F705 -> 105.26273 | J708: =Tyran!E705 -> 16.821858 | K708: =Fardo!E705 -> 13.610929 | L708: =Entworpe!E705 -> 10.833333 | M708: =B708+F708 -> 13
A709: 705 | B709: =Calopeia!D341 -> 2 | C709: =Sorange!B706 -> 10 | D709: =Tyran!B706 -> 22 | E709: =Fardo!B706 -> 6 | F709: =Entworpe!B706 -> 0 | G709: 1435 | H709: =Calopeia!I341 -> 11.940968 | I709: =Sorange!F706 -> 101.34138 | J709: =Tyran!E706 -> 16.174863 | K709: =Fardo!E706 -> 13.087432 | L709: =Entworpe!E706 -> 10.416667 | M709: =B709+F709 -> 2
A710: 706 | B710: =Calopeia!D342 -> 23 | C710: =Sorange!B707 -> 20 | D710: =Tyran!B707 -> 9 | E710: =Fardo!B707 -> 4 | F710: =Entworpe!B707 -> 0 | G710: 1436 | H710: =Calopeia!I342 -> 11.46333 | I710: =Sorange!F707 -> 97.409842 | J710: =Tyran!E707 -> 15.527869 | K710: =Fardo!E707 -> 12.563934 | L710: =Entworpe!E707 -> 10 | M710: =B710+F710 -> 23
A711: 707 | B711: =Calopeia!D343 -> 9 | C711: =Sorange!B708 -> 2 | D711: =Tyran!B708 -> 28 | E711: =Fardo!B708 -> 29 | F711: =Entworpe!B708 -> 0 | G711: 1437 | H711: =Calopeia!I343 -> 10.985691 | I711: =Sorange!F708 -> 93.468132 | J711: =Tyran!E708 -> 14.880874 | K711: =Fardo!E708 -> 12.040437 | L711: =Entworpe!E708 -> 9.5833333 | M711: =B711+F711 -> 9
A712: 708 | B712: =Calopeia!D344 -> 5 | C712: =Sorange!B709 -> 5 | D712: =Tyran!B709 -> 3 | E712: =Fardo!B709 -> 32 | F712: =Entworpe!B709 -> 0 | G712: 1438 | H712: =Calopeia!I344 -> 10.508052 | I712: =Sorange!F709 -> 89.516245 | J712: =Tyran!E709 -> 14.23388 | K712: =Fardo!E709 -> 11.51694 | L712: =Entworpe!E709 -> 9.1666667 | M712: =B712+F712 -> 5
A713: 709 | B713: =Calopeia!D345 -> 10 | C713: =Sorange!B710 -> 4 | D713: =Tyran!B710 -> 0 | E713: =Fardo!B710 -> 16 | F713: =Entworpe!B710 -> 0 | G713: 1439 | H713: =Calopeia!I345 -> 10.030413 | I713: =Sorange!F710 -> 85.554181 | J713: =Tyran!E710 -> 13.586885 | K713: =Fardo!E710 -> 10.993443 | L713: =Entworpe!E710 -> 8.75 | M713: =B713+F713 -> 10
A714: 710 | B714: =Calopeia!D346 -> 9 | C714: =Sorange!B711 -> 29 | D714: =Tyran!B711 -> 21 | E714: =Fardo!B711 -> 27 | F714: =Entworpe!B711 -> 0 | G714: 1440 | H714: =Calopeia!I346 -> 9.5527747 | I714: =Sorange!F711 -> 81.58194 | J714: =Tyran!E711 -> 12.939891 | K714: =Fardo!E711 -> 10.469945 | L714: =Entworpe!E711 -> 8.3333333 | M714: =B714+F714 -> 9
A715: 711 | B715: =Calopeia!D347 -> 10 | C715: =Sorange!B712 -> 2 | D715: =Tyran!B712 -> 21 | E715: =Fardo!B712 -> 0 | F715: =Entworpe!B712 -> 0 | G715: 1441 | H715: =Calopeia!I347 -> 9.075136 | I715: =Sorange!F712 -> 77.599522 | J715: =Tyran!E712 -> 12.292896 | K715: =Fardo!E712 -> 9.9464481 | L715: =Entworpe!E712 -> 7.9166667 | M715: =B715+F715 -> 10
... A734: 730 | B734: =Calopeia!D366 -> 10 | C734: =Sorange!B731 -> 10 | D734: =Tyran!B731 -> 2 | E734: =Fardo!B731 -> 3 | F734: =Entworpe!B731 -> 0 | G734: 1460 | H734: =Calopeia!I366 -> 0 | I734: =Sorange!F731 -> 0 | J734: =Tyran!E731 -> 0 | K734: =Fardo!E731 -> 0 | L734: =Entworpe!E731 -> 0 | M734: =B734+F734 -> 10

Sheet Calopeia
A1: day - 1st year | B1: Calopeia actual demand | C1: day - 2nd year | D1: Calopeia actual demand | E1: forecast - 3rd year | F1: forecast - seasonal | G1: forecast - 4th year | H1: forecast - seasonal | I1: from day 1430 | L1: Calopeia follows a ~365-day seasonal cycle, stable with no long-run trend.
A2: 1 | B2: 11 | C2: 366 | D2: 5 | E2: =A2+730 -> 731 | F2: =$P$18 -> 16.529495 | G2: =C2+730 -> 1096 | H2: =F2 -> 16.529495 | L2: Step 1. | M2: Overall average | N2: =AVERAGE(B2:B366,D2:D366) -> 39.193151
A3: 2 | B3: 7 | C3: 367 | D3: 4 | E3: =A3+730 -> 732 | F3: =$P$18 -> 16.529495 | G3: =C3+730 -> 1097 | H3: =F3 -> 16.529495 | M3: Trend level | N3: =AVERAGE(D2:D366) -> 38.621918
A4: 3 | B4: 4 | C4: 368 | D4: 9 | E4: =A4+730 -> 733 | F4: =$P$18 -> 16.529495 | G4: =C4+730 -> 1098 | H4: =F4 -> 16.529495
A5: 4 | B5: 8 | C5: 369 | D5: 9 | E5: =A5+730 -> 734 | F5: =$P$18 -> 16.529495 | G5: =C5+730 -> 1099 | H5: =F5 -> 16.529495 | M5: 10 phases | N5: From | O5: To | P5: Avg. per phase
A6: 5 | B6: 5 | C6: 370 | D6: 1 | E6: =A6+730 -> 735 | F6: =$P$18 -> 16.529495 | G6: =C6+730 -> 1100 | H6: =F6 -> 16.529495 | L6: 1st Trough | M6: 1 | N6: 1 | O6: =N6+72 -> 73 | P6: =AVERAGE(B2:B74) -> 16.60274
A7: 6 | B7: 8 | C7: 371 | D7: 29 | E7: =A7+730 -> 736 | F7: =$P$18 -> 16.529495 | G7: =C7+730 -> 1101 | H7: =F7 -> 16.529495 | L7: Ramp up | M7: 2 | N7: =O6+1 -> 74 | O7: =N7+72 -> 146 | P7: =AVERAGE(B75:B147) -> 48.972603
A8: 7 | B8: 14 | C8: 372 | D8: 6 | E8: =A8+730 -> 737 | F8: =$P$18 -> 16.529495 | G8: =C8+730 -> 1102 | H8: =F8 -> 16.529495 | L8: Peak | M8: 3 | N8: =O7+1 -> 147 | O8: =N8+72 -> 219 | P8: =AVERAGE(B148:B220) -> 70.780822
A9: 8 | B9: 6 | C9: 373 | D9: 4 | E9: =A9+730 -> 738 | F9: =$P$18 -> 16.529495 | G9: =C9+730 -> 1103 | H9: =F9 -> 16.529495 | L9: Decline | M9: 4 | N9: =O8+1 -> 220 | O9: =N9+72 -> 292 | P9: =AVERAGE(B221:B293) -> 48.931507
A10: 9 | B10: 31 | C10: 374 | D10: 1 | E10: =A10+730 -> 739 | F10: =$P$18 -> 16.529495 | G10: =C10+730 -> 1104 | H10: =F10 -> 16.529495 | L10: 2nd Trough | M10: 5 | N10: =O9+1 -> 293 | O10: =N10+72 -> 365 | P10: =AVERAGE(B294:B366) -> 13.534247
A11: 10 | B11: 7 | C11: 375 | D11: 13 | E11: =A11+730 -> 740 | F11: =$P$18 -> 16.529495 | G11: =C11+730 -> 1105 | H11: =F11 -> 16.529495 | L11: 1st Trough | M11: 6 | N11: =O10+1 -> 366 | O11: =N11+72 -> 438 | P11: =AVERAGE(D2:D74) -> 16.945205
A12: 11 | B12: 7 | C12: 376 | D12: 2 | E12: =A12+730 -> 741 | F12: =$P$18 -> 16.529495 | G12: =C12+730 -> 1106 | H12: =F12 -> 16.529495 | L12: Ramp up | M12: 7 | N12: =O11+1 -> 439 | O12: =N12+72 -> 511 | P12: =AVERAGE(D75:D147) -> 44.575342
A13: 12 | B13: 19 | C13: 377 | D13: 2 | E13: =A13+730 -> 742 | F13: =$P$18 -> 16.529495 | G13: =C13+730 -> 1107 | H13: =F13 -> 16.529495 | L13: Peak | M13: 8 | N13: =O12+1 -> 512 | O13: =N13+72 -> 584 | P13: =AVERAGE(D148:D220) -> 67.041096
A14: 13 | B14: 5 | C14: 378 | D14: 26 | E14: =A14+730 -> 743 | F14: =$P$18 -> 16.529495 | G14: =C14+730 -> 1108 | H14: =F14 -> 16.529495 | L14: Decline | M14: 9 | N14: =O13+1 -> 585 | O14: =N14+72 -> 657 | P14: =AVERAGE(D221:D293) -> 49
A15: 14 | B15: 6 | C15: 379 | D15: 6 | E15: =A15+730 -> 744 | F15: =$P$18 -> 16.529495 | G15: =C15+730 -> 1109 | H15: =F15 -> 16.529495 | L15: 2nd Trough | M15: 10 | N15: =O14+1 -> 658 | O15: =N15+72 -> 730 | P15: =AVERAGE(D294:D366) -> 15.547945
A16: 15 | B16: 7 | C16: 380 | D16: 2 | E16: =A16+730 -> 745 | F16: =$P$18 -> 16.529495 | G16: =C16+730 -> 1110 | H16: =F16 -> 16.529495
A17: 16 | B17: 5 | C17: 381 | D17: 18 | E17: =A17+730 -> 746 | F17: =$P$18 -> 16.529495 | G17: =C17+730 -> 1111 | H17: =F17 -> 16.529495 | L17: Step 2. | N17: Phase Average | O17: Seasonal Index (SI) | P17: Forecast Avg.
A18: 17 | B18: 14 | C18: 382 | D18: 11 | E18: =A18+730 -> 747 | F18: =$P$18 -> 16.529495 | G18: =C18+730 -> 1112 | H18: =F18 -> 16.529495 | M18: 1st Trough | N18: =AVERAGEIF($L$6:$L$15,M18,$P$6:$P$15) -> 16.773973 | O18: =N18/$N$2 -> 0.42798224 | P18: =O18*$N$3 -> 16.529495
A19: 18 | B19: 25 | C19: 383 | D19: 9 | E19: =A19+730 -> 748 | F19: =$P$18 -> 16.529495 | G19: =C19+730 -> 1113 | H19: =F19 -> 16.529495 | M19: Ramp up | N19: =AVERAGEIF($L$6:$L$15,M19,$P$6:$P$15) -> 46.773973 | O19: =N19/$N$2 -> 1.1934221 | P19: =O19*$N$3 -> 46.092251
A20: 19 | B20: 2 | C20: 384 | D20: 7 | E20: =A20+730 -> 749 | F20: =$P$18 -> 16.529495 | G20: =C20+730 -> 1114 | H20: =F20 -> 16.529495 | M20: Peak | N20: =AVERAGEIF($L$6:$L$15,M20,$P$6:$P$15) -> 68.910959 | O20: =N20/$N$2 -> 1.7582398 | P20: =O20*$N$3 -> 67.906595
A21: 20 | B21: 4 | C21: 385 | D21: 31 | E21: =A21+730 -> 750 | F21: =$P$18 -> 16.529495 | G21: =C21+730 -> 1115 | H21: =F21 -> 16.529495 | M21: Decline | N21: =AVERAGEIF($L$6:$L$15,M21,$P$6:$P$15) -> 48.965753 | O21: =N21/$N$2 -> 1.2493447 | P21: =O21*$N$3 -> 48.252087
A22: 21 | B22: 11 | C22: 386 | D22: 18 | E22: =A22+730 -> 751 | F22: =$P$18 -> 16.529495 | G22: =C22+730 -> 1116 | H22: =F22 -> 16.529495 | M22: 2nd Trough | N22: =AVERAGEIF($L$6:$L$15,M22,$P$6:$P$15) -> 14.541096 | O22: =N22/$N$2 -> 0.37101115 | P22: =O22*$N$3 -> 14.329162
A23: 22 | B23: 22 | C23: 387 | D23: 30 | E23: =A23+730 -> 752 | F23: =$P$18 -> 16.529495 | G23: =C23+730 -> 1117 | H23: =F23 -> 16.529495
A24: 23 | B24: 8 | C24: 388 | D24: 2 | E24: =A24+730 -> 753 | F24: =$P$18 -> 16.529495 | G24: =C24+730 -> 1118 | H24: =F24 -> 16.529495 | L24: Step 3. | N24: From | O24: To | P24: Forecast
A25: 24 | B25: 10 | C25: 389 | D25: 8 | E25: =A25+730 -> 754 | F25: =$P$18 -> 16.529495 | G25: =C25+730 -> 1119 | H25: =F25 -> 16.529495 | M25: 1st Trough | N25: =731 -> 731 | O25: =N25+72 -> 803 | P25: =AVERAGE($F$2:$F$74) -> 16.529495
A26: 25 | B26: 11 | C26: 390 | D26: 15 | E26: =A26+730 -> 755 | F26: =$P$18 -> 16.529495 | G26: =C26+730 -> 1120 | H26: =F26 -> 16.529495 | M26: Ramp up | N26: =O25+1 -> 804 | O26: =N26+72 -> 876 | P26: =AVERAGE($F$75:$F$147) -> 46.092251
A27: 26 | B27: 16 | C27: 391 | D27: 26 | E27: =A27+730 -> 756 | F27: =$P$18 -> 16.529495 | G27: =C27+730 -> 1121 | H27: =F27 -> 16.529495 | M27: Peak | N27: =O26+1 -> 877 | O27: =N27+72 -> 949 | P27: =AVERAGE($F$148:$F$220) -> 67.906595
A28: 27 | B28: 17 | C28: 392 | D28: 6 | E28: =A28+730 -> 757 | F28: =$P$18 -> 16.529495 | G28: =C28+730 -> 1122 | H28: =F28 -> 16.529495 | M28: Decline | N28: =O27+1 -> 950 | O28: =N28+72 -> 1022 | P28: =AVERAGE($F$221:$F$293) -> 48.252087
A29: 28 | B29: 12 | C29: 393 | D29: 16 | E29: =A29+730 -> 758 | F29: =$P$18 -> 16.529495 | G29: =C29+730 -> 1123 | H29: =F29 -> 16.529495 | M29: 2nd Trough | N29: =O28+1 -> 1023 | O29: =N29+72 -> 1095 | P29: =AVERAGE($F$294:$F$366) -> 14.329162
A30: 29 | B30: 7 | C30: 394 | D30: 13 | E30: =A30+730 -> 759 | F30: =$P$18 -> 16.529495 | G30: =C30+730 -> 1124 | H30: =F30 -> 16.529495 | M30: 1st Trough | N30: =O29+1 -> 1096 | O30: =N30+72 -> 1168 | P30: =AVERAGE($H$2:$H$74) -> 16.529495
A31: 30 | B31: 4 | C31: 395 | D31: 10 | E31: =A31+730 -> 760 | F31: =$P$18 -> 16.529495 | G31: =C31+730 -> 1125 | H31: =F31 -> 16.529495 | M31: Ramp up | N31: =O30+1 -> 1169 | O31: =N31+72 -> 1241 | P31: =AVERAGE($H$75:$H$147) -> 46.092251
A32: 31 | B32: 25 | C32: 396 | D32: 4 | E32: =A32+730 -> 761 | F32: =$P$18 -> 16.529495 | G32: =C32+730 -> 1126 | H32: =F32 -> 16.529495 | M32: Peak | N32: =O31+1 -> 1242 | O32: =N32+72 -> 1314 | P32: =AVERAGE($H$148:$H$220) -> 67.906595
A33: 32 | B33: 2 | C33: 397 | D33: 21 | E33: =A33+730 -> 762 | F33: =$P$18 -> 16.529495 | G33: =C33+730 -> 1127 | H33: =F33 -> 16.529495 | M33: Decline | N33: =O32+1 -> 1315 | O33: =N33+72 -> 1387 | P33: =AVERAGE($H$221:$H$293) -> 48.252087
A34: 33 | B34: 14 | C34: 398 | D34: 11 | E34: =A34+730 -> 763 | F34: =$P$18 -> 16.529495 | G34: =C34+730 -> 1128 | H34: =F34 -> 16.529495 | M34: 2nd Trough | N34: =O33+1 -> 1388 | O34: =N34+41 -> 1429 | P34: =AVERAGE($H$294:$H$335) -> 14.329162
A35: 34 | B35: 13 | C35: 399 | D35: 5 | E35: =A35+730 -> 764 | F35: =$P$18 -> 16.529495 | G35: =C35+730 -> 1129 | H35: =F35 -> 16.529495 | M35: From day 1430 | N35: =O34+1 -> 1430 | O35: =N35+30 -> 1460 | P35: =AVERAGE($I$336:$I$366) -> 7.1645811
A36: 35 | B36: 25 | C36: 400 | D36: 4 | E36: =A36+730 -> 765 | F36: =$P$18 -> 16.529495 | G36: =C36+730 -> 1130 | H36: =F36 -> 16.529495
A37: 36 | B37: 13 | C37: 401 | D37: 18 | E37: =A37+730 -> 766 | F37: =$P$18 -> 16.529495 | G37: =C37+730 -> 1131 | H37: =F37 -> 16.529495
A38: 37 | B38: 8 | C38: 402 | D38: 21 | E38: =A38+730 -> 767 | F38: =$P$18 -> 16.529495 | G38: =C38+730 -> 1132 | H38: =F38 -> 16.529495
A39: 38 | B39: 17 | C39: 403 | D39: 24 | E39: =A39+730 -> 768 | F39: =$P$18 -> 16.529495 | G39: =C39+730 -> 1133 | H39: =F39 -> 16.529495
A40: 39 | B40: 24 | C40: 404 | D40: 4 | E40: =A40+730 -> 769 | F40: =$P$18 -> 16.529495 | G40: =C40+730 -> 1134 | H40: =F40 -> 16.529495
A41: 40 | B41: 6 | C41: 405 | D41: 5 | E41: =A41+730 -> 770 | F41: =$P$18 -> 16.529495 | G41: =C41+730 -> 1135 | H41: =F41 -> 16.529495
A42: 41 | B42: 19 | C42: 406 | D42: 12 | E42: =A42+730 -> 771 | F42: =$P$18 -> 16.529495 | G42: =C42+730 -> 1136 | H42: =F42 -> 16.529495
A43: 42 | B43: 33 | C43: 407 | D43: 18 | E43: =A43+730 -> 772 | F43: =$P$18 -> 16.529495 | G43: =C43+730 -> 1137 | H43: =F43 -> 16.529495
A44: 43 | B44: 7 | C44: 408 | D44: 10 | E44: =A44+730 -> 773 | F44: =$P$18 -> 16.529495 | G44: =C44+730 -> 1138 | H44: =F44 -> 16.529495
A45: 44 | B45: 18 | C45: 409 | D45: 9 | E45: =A45+730 -> 774 | F45: =$P$18 -> 16.529495 | G45: =C45+730 -> 1139 | H45: =F45 -> 16.529495
A46: 45 | B46: 12 | C46: 410 | D46: 33 | E46: =A46+730 -> 775 | F46: =$P$18 -> 16.529495 | G46: =C46+730 -> 1140 | H46: =F46 -> 16.529495
A47: 46 | B47: 7 | C47: 411 | D47: 22 | E47: =A47+730 -> 776 | F47: =$P$18 -> 16.529495 | G47: =C47+730 -> 1141 | H47: =F47 -> 16.529495
... A74: 73 | B74: 50 | C74: 438 | D74: 28 | E74: =A74+730 -> 803 | F74: =$P$18 -> 16.529495 | G74: =C74+730 -> 1168 | H74: =F74 -> 16.529495
A75: 74 | B75: 39 | C75: 439 | D75: 48 | E75: =A75+730 -> 804 | F75: =$P$19 -> 46.092251 | G75: =C75+730 -> 1169 | H75: =F75 -> 46.092251
A76: 75 | B76: 50 | C76: 440 | D76: 14 | E76: =A76+730 -> 805 | F76: =$P$19 -> 46.092251 | G76: =C76+730 -> 1170 | H76: =F76 -> 46.092251
A77: 76 | B77: 35 | C77: 441 | D77: 26 | E77: =A77+730 -> 806 | F77: =$P$19 -> 46.092251 | G77: =C77+730 -> 1171 | H77: =F77 -> 46.092251
A78: 77 | B78: 45 | C78: 442 | D78: 46 | E78: =A78+730 -> 807 | F78: =$P$19 -> 46.092251 | G78: =C78+730 -> 1172 | H78: =F78 -> 46.092251
A79: 78 | B79: 69 | C79: 443 | D79: 38 | E79: =A79+730 -> 808 | F79: =$P$19 -> 46.092251 | G79: =C79+730 -> 1173 | H79: =F79 -> 46.092251
A80: 79 | B80: 38 | C80: 444 | D80: 13 | E80: =A80+730 -> 809 | F80: =$P$19 -> 46.092251 | G80: =C80+730 -> 1174 | H80: =F80 -> 46.092251
A81: 80 | B81: 23 | C81: 445 | D81: 19 | E81: =A81+730 -> 810 | F81: =$P$19 -> 46.092251 | G81: =C81+730 -> 1175 | H81: =F81 -> 46.092251
A82: 81 | B82: 19 | C82: 446 | D82: 48 | E82: =A82+730 -> 811 | F82: =$P$19 -> 46.092251 | G82: =C82+730 -> 1176 | H82: =F82 -> 46.092251
A83: 82 | B83: 42 | C83: 447 | D83: 37 | E83: =A83+730 -> 812 | F83: =$P$19 -> 46.092251 | G83: =C83+730 -> 1177 | H83: =F83 -> 46.092251
A84: 83 | B84: 39 | C84: 448 | D84: 49 | E84: =A84+730 -> 813 | F84: =$P$19 -> 46.092251 | G84: =C84+730 -> 1178 | H84: =F84 -> 46.092251
A85: 84 | B85: 27 | C85: 449 | D85: 40 | E85: =A85+730 -> 814 | F85: =$P$19 -> 46.092251 | G85: =C85+730 -> 1179 | H85: =F85 -> 46.092251
A86: 85 | B86: 19 | C86: 450 | D86: 49 | E86: =A86+730 -> 815 | F86: =$P$19 -> 46.092251 | G86: =C86+730 -> 1180 | H86: =F86 -> 46.092251
... A147: 146 | B147: 83 | C147: 511 | D147: 90 | E147: =A147+730 -> 876 | F147: =$P$19 -> 46.092251 | G147: =C147+730 -> 1241 | H147: =F147 -> 46.092251
A148: 147 | B148: 57 | C148: 512 | D148: 27 | E148: =A148+730 -> 877 | F148: =$P$20 -> 67.906595 | G148: =C148+730 -> 1242 | H148: =F148 -> 67.906595
A149: 148 | B149: 61 | C149: 513 | D149: 32 | E149: =A149+730 -> 878 | F149: =$P$20 -> 67.906595 | G149: =C149+730 -> 1243 | H149: =F149 -> 67.906595
A150: 149 | B150: 81 | C150: 514 | D150: 58 | E150: =A150+730 -> 879 | F150: =$P$20 -> 67.906595 | G150: =C150+730 -> 1244 | H150: =F150 -> 67.906595
A151: 150 | B151: 59 | C151: 515 | D151: 78 | E151: =A151+730 -> 880 | F151: =$P$20 -> 67.906595 | G151: =C151+730 -> 1245 | H151: =F151 -> 67.906595
A152: 151 | B152: 51 | C152: 516 | D152: 48 | E152: =A152+730 -> 881 | F152: =$P$20 -> 67.906595 | G152: =C152+730 -> 1246 | H152: =F152 -> 67.906595
A153: 152 | B153: 68 | C153: 517 | D153: 97 | E153: =A153+730 -> 882 | F153: =$P$20 -> 67.906595 | G153: =C153+730 -> 1247 | H153: =F153 -> 67.906595
A154: 153 | B154: 101 | C154: 518 | D154: 106 | E154: =A154+730 -> 883 | F154: =$P$20 -> 67.906595 | G154: =C154+730 -> 1248 | H154: =F154 -> 67.906595
A155: 154 | B155: 80 | C155: 519 | D155: 53 | E155: =A155+730 -> 884 | F155: =$P$20 -> 67.906595 | G155: =C155+730 -> 1249 | H155: =F155 -> 67.906595
A156: 155 | B156: 43 | C156: 520 | D156: 43 | E156: =A156+730 -> 885 | F156: =$P$20 -> 67.906595 | G156: =C156+730 -> 1250 | H156: =F156 -> 67.906595
A157: 156 | B157: 64 | C157: 521 | D157: 59 | E157: =A157+730 -> 886 | F157: =$P$20 -> 67.906595 | G157: =C157+730 -> 1251 | H157: =F157 -> 67.906595
A158: 157 | B158: 89 | C158: 522 | D158: 28 | E158: =A158+730 -> 887 | F158: =$P$20 -> 67.906595 | G158: =C158+730 -> 1252 | H158: =F158 -> 67.906595
A159: 158 | B159: 94 | C159: 523 | D159: 70 | E159: =A159+730 -> 888 | F159: =$P$20 -> 67.906595 | G159: =C159+730 -> 1253 | H159: =F159 -> 67.906595
... A220: 219 | B220: 64 | C220: 584 | D220: 52 | E220: =A220+730 -> 949 | F220: =$P$20 -> 67.906595 | G220: =C220+730 -> 1314 | H220: =F220 -> 67.906595
A221: 220 | B221: 40 | C221: 585 | D221: 73 | E221: =A221+730 -> 950 | F221: =$P$21 -> 48.252087 | G221: =C221+730 -> 1315 | H221: =F221 -> 48.252087
A222: 221 | B222: 64 | C222: 586 | D222: 58 | E222: =A222+730 -> 951 | F222: =$P$21 -> 48.252087 | G222: =C222+730 -> 1316 | H222: =F222 -> 48.252087
A223: 222 | B223: 56 | C223: 587 | D223: 93 | E223: =A223+730 -> 952 | F223: =$P$21 -> 48.252087 | G223: =C223+730 -> 1317 | H223: =F223 -> 48.252087
A224: 223 | B224: 78 | C224: 588 | D224: 33 | E224: =A224+730 -> 953 | F224: =$P$21 -> 48.252087 | G224: =C224+730 -> 1318 | H224: =F224 -> 48.252087
A225: 224 | B225: 43 | C225: 589 | D225: 42 | E225: =A225+730 -> 954 | F225: =$P$21 -> 48.252087 | G225: =C225+730 -> 1319 | H225: =F225 -> 48.252087
A226: 225 | B226: 78 | C226: 590 | D226: 59 | E226: =A226+730 -> 955 | F226: =$P$21 -> 48.252087 | G226: =C226+730 -> 1320 | H226: =F226 -> 48.252087
A227: 226 | B227: 64 | C227: 591 | D227: 75 | E227: =A227+730 -> 956 | F227: =$P$21 -> 48.252087 | G227: =C227+730 -> 1321 | H227: =F227 -> 48.252087
A228: 227 | B228: 67 | C228: 592 | D228: 34 | E228: =A228+730 -> 957 | F228: =$P$21 -> 48.252087 | G228: =C228+730 -> 1322 | H228: =F228 -> 48.252087
A229: 228 | B229: 80 | C229: 593 | D229: 77 | E229: =A229+730 -> 958 | F229: =$P$21 -> 48.252087 | G229: =C229+730 -> 1323 | H229: =F229 -> 48.252087
A230: 229 | B230: 40 | C230: 594 | D230: 64 | E230: =A230+730 -> 959 | F230: =$P$21 -> 48.252087 | G230: =C230+730 -> 1324 | H230: =F230 -> 48.252087
A231: 230 | B231: 71 | C231: 595 | D231: 57 | E231: =A231+730 -> 960 | F231: =$P$21 -> 48.252087 | G231: =C231+730 -> 1325 | H231: =F231 -> 48.252087
A232: 231 | B232: 84 | C232: 596 | D232: 91 | E232: =A232+730 -> 961 | F232: =$P$21 -> 48.252087 | G232: =C232+730 -> 1326 | H232: =F232 -> 48.252087
... A293: 292 | B293: 20 | C293: 657 | D293: 16 | E293: =A293+730 -> 1022 | F293: =$P$21 -> 48.252087 | G293: =C293+730 -> 1387 | H293: =F293 -> 48.252087
A294: 293 | B294: 29 | C294: 658 | D294: 15 | E294: =A294+730 -> 1023 | F294: =$P$22 -> 14.329162 | G294: =C294+730 -> 1388 | H294: =F294 -> 14.329162
A295: 294 | B295: 18 | C295: 659 | D295: 17 | E295: =A295+730 -> 1024 | F295: =$P$22 -> 14.329162 | G295: =C295+730 -> 1389 | H295: =F295 -> 14.329162
A296: 295 | B296: 62 | C296: 660 | D296: 14 | E296: =A296+730 -> 1025 | F296: =$P$22 -> 14.329162 | G296: =C296+730 -> 1390 | H296: =F296 -> 14.329162
A297: 296 | B297: 10 | C297: 661 | D297: 54 | E297: =A297+730 -> 1026 | F297: =$P$22 -> 14.329162 | G297: =C297+730 -> 1391 | H297: =F297 -> 14.329162
A298: 297 | B298: 4 | C298: 662 | D298: 17 | E298: =A298+730 -> 1027 | F298: =$P$22 -> 14.329162 | G298: =C298+730 -> 1392 | H298: =F298 -> 14.329162
A299: 298 | B299: 23 | C299: 663 | D299: 33 | E299: =A299+730 -> 1028 | F299: =$P$22 -> 14.329162 | G299: =C299+730 -> 1393 | H299: =F299 -> 14.329162
A300: 299 | B300: 14 | C300: 664 | D300: 12 | E300: =A300+730 -> 1029 | F300: =$P$22 -> 14.329162 | G300: =C300+730 -> 1394 | H300: =F300 -> 14.329162
A301: 300 | B301: 34 | C301: 665 | D301: 15 | E301: =A301+730 -> 1030 | F301: =$P$22 -> 14.329162 | G301: =C301+730 -> 1395 | H301: =F301 -> 14.329162
A302: 301 | B302: 10 | C302: 666 | D302: 21 | E302: =A302+730 -> 1031 | F302: =$P$22 -> 14.329162 | G302: =C302+730 -> 1396 | H302: =F302 -> 14.329162
A303: 302 | B303: 10 | C303: 667 | D303: 16 | E303: =A303+730 -> 1032 | F303: =$P$22 -> 14.329162 | G303: =C303+730 -> 1397 | H303: =F303 -> 14.329162
A304: 303 | B304: 14 | C304: 668 | D304: 24 | E304: =A304+730 -> 1033 | F304: =$P$22 -> 14.329162 | G304: =C304+730 -> 1398 | H304: =F304 -> 14.329162
A305: 304 | B305: 16 | C305: 669 | D305: 19 | E305: =A305+730 -> 1034 | F305: =$P$22 -> 14.329162 | G305: =C305+730 -> 1399 | H305: =F305 -> 14.329162
... A335: 334 | B335: 2 | C335: 699 | D335: 10 | E335: =A335+730 -> 1064 | F335: =$P$22 -> 14.329162 | G335: =C335+730 -> 1429 | H335: =F335 -> 14.329162
...

Sheet Sorange
A1: day | B1: Sorange | C1: forecast - day | D1: relative index | E1: forecast - linear regression | F1: from day 1430 | H1: Grows linearly from day 640 to day 1430, then decays to zero by day 1460.
A2: 1 | B2: 0 | C2: =A2+730 -> 731 | D2: =C2-640+1 -> 92 | E2: =$I$16*D2+$I$17 -> 14.142857 | I2: From | J2: To | K2: Forecast
A3: 2 | B3: 0 | C3: =A3+730 -> 732 | D3: =C3-640+1 -> 93 | E3: =$I$16*D3+$I$17 -> 14.295509 | H3: 1st Trough | I3: =731 -> 731 | J3: =I3+72 -> 803 | K3: =AVERAGE($E$2:$E$74) -> 19.638318
A4: 3 | B4: 0 | C4: =A4+730 -> 733 | D4: =C4-640+1 -> 94 | E4: =$I$16*D4+$I$17 -> 14.448161 | H4: Ramp up | I4: =J3+1 -> 804 | J4: =I4+72 -> 876 | K4: =AVERAGE($E$75:$E$147) -> 30.781892
A5: 4 | B5: 0 | C5: =A5+730 -> 734 | D5: =C5-640+1 -> 95 | E5: =$I$16*D5+$I$17 -> 14.600812 | H5: Peak | I5: =J4+1 -> 877 | J5: =I5+72 -> 949 | K5: =AVERAGE($E$148:$E$220) -> 41.925466
A6: 5 | B6: 0 | C6: =A6+730 -> 735 | D6: =C6-640+1 -> 96 | E6: =$I$16*D6+$I$17 -> 14.753464 | H6: Decline | I6: =J5+1 -> 950 | J6: =I6+72 -> 1022 | K6: =AVERAGE($E$221:$E$293) -> 53.06904
A7: 6 | B7: 0 | C7: =A7+730 -> 736 | D7: =C7-640+1 -> 97 | E7: =$I$16*D7+$I$17 -> 14.906116 | H7: 2nd Trough | I7: =J6+1 -> 1023 | J7: =I7+72 -> 1095 | K7: =AVERAGE($E$294:$E$366) -> 64.212613
A8: 7 | B8: 0 | C8: =A8+730 -> 737 | D8: =C8-640+1 -> 98 | E8: =$I$16*D8+$I$17 -> 15.058767 | H8: 1st Trough | I8: =J7+1 -> 1096 | J8: =I8+72 -> 1168 | K8: =AVERAGE($E$367:$E$439) -> 75.356187
A9: 8 | B9: 0 | C9: =A9+730 -> 738 | D9: =C9-640+1 -> 99 | E9: =$I$16*D9+$I$17 -> 15.211419 | H9: Ramp up | I9: =J8+1 -> 1169 | J9: =I9+72 -> 1241 | K9: =AVERAGE($E$440:$E$512) -> 86.499761
A10: 9 | B10: 0 | C10: =A10+730 -> 739 | D10: =C10-640+1 -> 100 | E10: =$I$16*D10+$I$17 -> 15.364071 | H10: Peak | I10: =J9+1 -> 1242 | J10: =I10+72 -> 1314 | K10: =AVERAGE($E$513:$E$585) -> 97.643335
A11: 10 | B11: 0 | C11: =A11+730 -> 740 | D11: =C11-640+1 -> 101 | E11: =$I$16*D11+$I$17 -> 15.516722 | H11: Decline | I11: =J10+1 -> 1315 | J11: =I11+72 -> 1387 | K11: =AVERAGE($E$586:$E$658) -> 108.78691
A12: 11 | B12: 0 | C12: =A12+730 -> 741 | D12: =C12-640+1 -> 102 | E12: =$I$16*D12+$I$17 -> 15.669374 | H12: 2nd Trough | I12: =J11+1 -> 1388 | J12: =I12+41 -> 1429 | K12: =AVERAGE($E$659:$E$700) -> 117.56438
A13: 12 | B13: 0 | C13: =A13+730 -> 742 | D13: =C13-640+1 -> 103 | E13: =$I$16*D13+$I$17 -> 15.822026 | H13: From day 1430 | I13: =J12+1 -> 1430 | J13: =I13+30 -> 1460 | K13: =AVERAGE($F$701:$F$731) -> 61.161013
A14: 13 | B14: 0 | C14: =A14+730 -> 743 | D14: =C14-640+1 -> 104 | E14: =$I$16*D14+$I$17 -> 15.974677
A15: 14 | B15: 0 | C15: =A15+730 -> 744 | D15: =C15-640+1 -> 105 | E15: =$I$16*D15+$I$17 -> 16.127329 | H15: OLS fit: day 640 - 730, t = day - 640 + 1
A16: 15 | B16: 0 | C16: =A16+730 -> 745 | D16: =C16-640+1 -> 106 | E16: =$I$16*D16+$I$17 -> 16.279981 | H16: b (slope) | I16: {=SLOPE($B$641:$B$731,$A$641:$A$731-640+1)} -> 0.1526517
A17: 16 | B17: 0 | C17: =A17+730 -> 746 | D17: =C17-640+1 -> 107 | E17: =$I$16*D17+$I$17 -> 16.432633 | H17: a (intercept) | I17: {=INTERCEPT($B$641:$B$731,$A$641:$A$731-640+1)} -> 0.098901099
A18: 17 | B18: 0 | C18: =A18+730 -> 747 | D18: =C18-640+1 -> 108 | E18: =$I$16*D18+$I$17 -> 16.585284
A19: 18 | B19: 0 | C19: =A19+730 -> 748 | D19: =C19-640+1 -> 109 | E19: =$I$16*D19+$I$17 -> 16.737936
A20: 19 | B20: 0 | C20: =A20+730 -> 749 | D20: =C20-640+1 -> 110 | E20: =$I$16*D20+$I$17 -> 16.890588
A21: 20 | B21: 0 | C21: =A21+730 -> 750 | D21: =C21-640+1 -> 111 | E21: =$I$16*D21+$I$17 -> 17.043239
A22: 21 | B22: 0 | C22: =A22+730 -> 751 | D22: =C22-640+1 -> 112 | E22: =$I$16*D22+$I$17 -> 17.195891
A23: 22 | B23: 0 | C23: =A23+730 -> 752 | D23: =C23-640+1 -> 113 | E23: =$I$16*D23+$I$17 -> 17.348543
A24: 23 | B24: 0 | C24: =A24+730 -> 753 | D24: =C24-640+1 -> 114 | E24: =$I$16*D24+$I$17 -> 17.501194
A25: 24 | B25: 0 | C25: =A25+730 -> 754 | D25: =C25-640+1 -> 115 | E25: =$I$16*D25+$I$17 -> 17.653846
A26: 25 | B26: 0 | C26: =A26+730 -> 755 | D26: =C26-640+1 -> 116 | E26: =$I$16*D26+$I$17 -> 17.806498
A27: 26 | B27: 0 | C27: =A27+730 -> 756 | D27: =C27-640+1 -> 117 | E27: =$I$16*D27+$I$17 -> 17.95915
A28: 27 | B28: 0 | C28: =A28+730 -> 757 | D28: =C28-640+1 -> 118 | E28: =$I$16*D28+$I$17 -> 18.111801
A29: 28 | B29: 0 | C29: =A29+730 -> 758 | D29: =C29-640+1 -> 119 | E29: =$I$16*D29+$I$17 -> 18.264453
... A700: 699 | B700: 8 | C700: =A700+730 -> 1429 | D700: =C700-640+1 -> 790 | E700: =$I$16*D700+$I$17 -> 120.69374
A701: 700 | B701: 18 | C701: =A701+730 -> 1430 | D701: =C701-640+1 -> 791 | E701: =$I$16*D701+$I$17 -> 120.84639 | F701: =E701*(1460-C701)/30 -> 120.84639
A702: 701 | B702: 2 | C702: =A702+730 -> 1431 | D702: =C702-640+1 -> 792 | E702: =$I$16*D702+$I$17 -> 120.99904 | F702: =E702*(1460-C702)/30 -> 116.96574
A703: 702 | B703: 11 | C703: =A703+730 -> 1432 | D703: =C703-640+1 -> 793 | E703: =$I$16*D703+$I$17 -> 121.1517 | F703: =E703*(1460-C703)/30 -> 113.07492
A704: 703 | B704: 3 | C704: =A704+730 -> 1433 | D704: =C704-640+1 -> 794 | E704: =$I$16*D704+$I$17 -> 121.30435 | F704: =E704*(1460-C704)/30 -> 109.17391
A705: 704 | B705: 4 | C705: =A705+730 -> 1434 | D705: =C705-640+1 -> 795 | E705: =$I$16*D705+$I$17 -> 121.457 | F705: =E705*(1460-C705)/30 -> 105.26273
A706: 705 | B706: 10 | C706: =A706+730 -> 1435 | D706: =C706-640+1 -> 796 | E706: =$I$16*D706+$I$17 -> 121.60965 | F706: =E706*(1460-C706)/30 -> 101.34138
A707: 706 | B707: 20 | C707: =A707+730 -> 1436 | D707: =C707-640+1 -> 797 | E707: =$I$16*D707+$I$17 -> 121.7623 | F707: =E707*(1460-C707)/30 -> 97.409842
A708: 707 | B708: 2 | C708: =A708+730 -> 1437 | D708: =C708-640+1 -> 798 | E708: =$I$16*D708+$I$17 -> 121.91495 | F708: =E708*(1460-C708)/30 -> 93.468132
A709: 708 | B709: 5 | C709: =A709+730 -> 1438 | D709: =C709-640+1 -> 799 | E709: =$I$16*D709+$I$17 -> 122.06761 | F709: =E709*(1460-C709)/30 -> 89.516245
A710: 709 | B710: 4 | C710: =A710+730 -> 1439 | D710: =C710-640+1 -> 800 | E710: =$I$16*D710+$I$17 -> 122.22026 | F710: =E710*(1460-C710)/30 -> 85.554181
A711: 710 | B711: 29 | C711: =A711+730 -> 1440 | D711: =C711-640+1 -> 801 | E711: =$I$16*D711+$I$17 -> 122.37291 | F711: =E711*(1460-C711)/30 -> 81.58194
A712: 711 | B712: 2 | C712: =A712+730 -> 1441 | D712: =C712-640+1 -> 802 | E712: =$I$16*D712+$I$17 -> 122.52556 | F712: =E712*(1460-C712)/30 -> 77.599522
... A731: 730 | B731: 10 | C731: =A731+730 -> 1460 | D731: =C731-640+1 -> 821 | E731: =$I$16*D731+$I$17 -> 125.42594 | F731: =E731*(1460-C731)/30 -> 0

Sheet Tyran
A1: day | B1: Tyran | C1: forecast - day | D1: forecast - simple historical avg. | E1: from day 1430 | G1: Demand started ~0 on day 640 and gradually ramped up over ~30 days to reach its steady-state level.
A2: 1 | B2: 0 | C2: =A2+730 -> 731 | D2: =AVERAGE(B671:B731) -> 19.409836 | G2: If we include the ramp-up days in the simple average >> underestimate the true long-run average because those early low values pull the mean down.
A3: 2 | B3: 0 | C3: =A3+730 -> 732 | D3: =$D$2 -> 19.409836 | G3: >> use only day 670 - 730 (after ramp-up completes) for the simple average
A4: 3 | B4: 0 | C4: =A4+730 -> 733 | D4: =$D$2 -> 19.409836
A5: 4 | B5: 0 | C5: =A5+730 -> 734 | D5: =$D$2 -> 19.409836 | H5: From | I5: To | J5: Forecast
A6: 5 | B6: 0 | C6: =A6+730 -> 735 | D6: =$D$2 -> 19.409836 | G6: 1st Trough | H6: =731 -> 731 | I6: =H6+72 -> 803 | J6: =AVERAGE($D$2:$D$74) -> 19.409836
A7: 6 | B7: 0 | C7: =A7+730 -> 736 | D7: =$D$2 -> 19.409836 | G7: Ramp up | H7: =I6+1 -> 804 | I7: =H7+72 -> 876 | J7: =AVERAGE($D$75:$D$147) -> 19.409836
A8: 7 | B8: 0 | C8: =A8+730 -> 737 | D8: =$D$2 -> 19.409836 | G8: Peak | H8: =I7+1 -> 877 | I8: =H8+72 -> 949 | J8: =AVERAGE($D$148:$D$220) -> 19.409836
A9: 8 | B9: 0 | C9: =A9+730 -> 738 | D9: =$D$2 -> 19.409836 | G9: Decline | H9: =I8+1 -> 950 | I9: =H9+72 -> 1022 | J9: =AVERAGE($D$221:$D$293) -> 19.409836
A10: 9 | B10: 0 | C10: =A10+730 -> 739 | D10: =$D$2 -> 19.409836 | G10: 2nd Trough | H10: =I9+1 -> 1023 | I10: =H10+72 -> 1095 | J10: =AVERAGE($D$294:$D$366) -> 19.409836
A11: 10 | B11: 0 | C11: =A11+730 -> 740 | D11: =$D$2 -> 19.409836 | G11: 1st Trough | H11: =I10+1 -> 1096 | I11: =H11+72 -> 1168 | J11: =AVERAGE($D$367:$D$439) -> 19.409836
A12: 11 | B12: 0 | C12: =A12+730 -> 741 | D12: =$D$2 -> 19.409836 | G12: Ramp up | H12: =I11+1 -> 1169 | I12: =H12+72 -> 1241 | J12: =AVERAGE($D$440:$D$512) -> 19.409836
A13: 12 | B13: 0 | C13: =A13+730 -> 742 | D13: =$D$2 -> 19.409836 | G13: Peak | H13: =I12+1 -> 1242 | I13: =H13+72 -> 1314 | J13: =AVERAGE($D$513:$D$585) -> 19.409836
A14: 13 | B14: 0 | C14: =A14+730 -> 743 | D14: =$D$2 -> 19.409836 | G14: Decline | H14: =I13+1 -> 1315 | I14: =H14+72 -> 1387 | J14: =AVERAGE($D$586:$D$658) -> 19.409836
A15: 14 | B15: 0 | C15: =A15+730 -> 744 | D15: =$D$2 -> 19.409836 | G15: 2nd Trough | H15: =I14+1 -> 1388 | I15: =H15+41 -> 1429 | J15: =AVERAGE($D$659:$D$700) -> 19.409836
A16: 15 | B16: 0 | C16: =A16+730 -> 745 | D16: =$D$2 -> 19.409836 | G16: From day 1430 | H16: =I15+1 -> 1430 | I16: =H16+30 -> 1460 | J16: =AVERAGE($E$701:$E$731) -> 9.704918
A17: 16 | B17: 0 | C17: =A17+730 -> 746 | D17: =$D$2 -> 19.409836
A18: 17 | B18: 0 | C18: =A18+730 -> 747 | D18: =$D$2 -> 19.409836
A19: 18 | B19: 0 | C19: =A19+730 -> 748 | D19: =$D$2 -> 19.409836
A20: 19 | B20: 0 | C20: =A20+730 -> 749 | D20: =$D$2 -> 19.409836
A21: 20 | B21: 0 | C21: =A21+730 -> 750 | D21: =$D$2 -> 19.409836
A22: 21 | B22: 0 | C22: =A22+730 -> 751 | D22: =$D$2 -> 19.409836
A23: 22 | B23: 0 | C23: =A23+730 -> 752 | D23: =$D$2 -> 19.409836
A24: 23 | B24: 0 | C24: =A24+730 -> 753 | D24: =$D$2 -> 19.409836
A25: 24 | B25: 0 | C25: =A25+730 -> 754 | D25: =$D$2 -> 19.409836
A26: 25 | B26: 0 | C26: =A26+730 -> 755 | D26: =$D$2 -> 19.409836
A27: 26 | B27: 0 | C27: =A27+730 -> 756 | D27: =$D$2 -> 19.409836
A28: 27 | B28: 0 | C28: =A28+730 -> 757 | D28: =$D$2 -> 19.409836
... A700: 699 | B700: 9 | C700: =A700+730 -> 1429 | D700: =$D$2 -> 19.409836
A701: 700 | B701: 47 | C701: =A701+730 -> 1430 | D701: =$D$2 -> 19.409836 | E701: =D701*(1460-C701)/30 -> 19.409836
A702: 701 | B702: 0 | C702: =A702+730 -> 1431 | D702: =$D$2 -> 19.409836 | E702: =D702*(1460-C702)/30 -> 18.762842
A703: 702 | B703: 0 | C703: =A703+730 -> 1432 | D703: =$D$2 -> 19.409836 | E703: =D703*(1460-C703)/30 -> 18.115847
A704: 703 | B704: 10 | C704: =A704+730 -> 1433 | D704: =$D$2 -> 19.409836 | E704: =D704*(1460-C704)/30 -> 17.468852
A705: 704 | B705: 24 | C705: =A705+730 -> 1434 | D705: =$D$2 -> 19.409836 | E705: =D705*(1460-C705)/30 -> 16.821858
A706: 705 | B706: 22 | C706: =A706+730 -> 1435 | D706: =$D$2 -> 19.409836 | E706: =D706*(1460-C706)/30 -> 16.174863
A707: 706 | B707: 9 | C707: =A707+730 -> 1436 | D707: =$D$2 -> 19.409836 | E707: =D707*(1460-C707)/30 -> 15.527869
A708: 707 | B708: 28 | C708: =A708+730 -> 1437 | D708: =$D$2 -> 19.409836 | E708: =D708*(1460-C708)/30 -> 14.880874
A709: 708 | B709: 3 | C709: =A709+730 -> 1438 | D709: =$D$2 -> 19.409836 | E709: =D709*(1460-C709)/30 -> 14.23388
A710: 709 | B710: 0 | C710: =A710+730 -> 1439 | D710: =$D$2 -> 19.409836 | E710: =D710*(1460-C710)/30 -> 13.586885
A711: 710 | B711: 21 | C711: =A711+730 -> 1440 | D711: =$D$2 -> 19.409836 | E711: =D711*(1460-C711)/30 -> 12.939891
A712: 711 | B712: 21 | C712: =A712+730 -> 1441 | D712: =$D$2 -> 19.409836 | E712: =D712*(1460-C712)/30 -> 12.292896
... A731: 730 | B731: 2 | C731: =A731+730 -> 1460 | D731: =$D$2 -> 19.409836 | E731: =D731*(1460-C731)/30 -> 0

Sheet Fardo
A1: day | B1: Fardo | C1: forecast - day | D1: forecast - simple historical avg. | E1: from day 1430
A2: 1 | B2: 0 | C2: =A2+730 -> 731 | D2: =AVERAGE(B671:B731) -> 15.704918 | G2: Same as Tyran
A3: 2 | B3: 0 | C3: =A3+730 -> 732 | D3: =$D$2 -> 15.704918
A4: 3 | B4: 0 | C4: =A4+730 -> 733 | D4: =$D$2 -> 15.704918 | H4: From | I4: To | J4: Forecast
A5: 4 | B5: 0 | C5: =A5+730 -> 734 | D5: =$D$2 -> 15.704918 | G5: 1st Trough | H5: =731 -> 731 | I5: =H5+72 -> 803 | J5: =AVERAGE($D$2:$D$74) -> 15.704918
A6: 5 | B6: 0 | C6: =A6+730 -> 735 | D6: =$D$2 -> 15.704918 | G6: Ramp up | H6: =I5+1 -> 804 | I6: =H6+72 -> 876 | J6: =AVERAGE($D$75:$D$147) -> 15.704918
A7: 6 | B7: 0 | C7: =A7+730 -> 736 | D7: =$D$2 -> 15.704918 | G7: Peak | H7: =I6+1 -> 877 | I7: =H7+72 -> 949 | J7: =AVERAGE($D$148:$D$220) -> 15.704918
A8: 7 | B8: 0 | C8: =A8+730 -> 737 | D8: =$D$2 -> 15.704918 | G8: Decline | H8: =I7+1 -> 950 | I8: =H8+72 -> 1022 | J8: =AVERAGE($D$221:$D$293) -> 15.704918
A9: 8 | B9: 0 | C9: =A9+730 -> 738 | D9: =$D$2 -> 15.704918 | G9: 2nd Trough | H9: =I8+1 -> 1023 | I9: =H9+72 -> 1095 | J9: =AVERAGE($D$294:$D$366) -> 15.704918
A10: 9 | B10: 0 | C10: =A10+730 -> 739 | D10: =$D$2 -> 15.704918 | G10: 1st Trough | H10: =I9+1 -> 1096 | I10: =H10+72 -> 1168 | J10: =AVERAGE($D$367:$D$439) -> 15.704918
A11: 10 | B11: 0 | C11: =A11+730 -> 740 | D11: =$D$2 -> 15.704918 | G11: Ramp up | H11: =I10+1 -> 1169 | I11: =H11+72 -> 1241 | J11: =AVERAGE($D$440:$D$512) -> 15.704918
A12: 11 | B12: 0 | C12: =A12+730 -> 741 | D12: =$D$2 -> 15.704918 | G12: Peak | H12: =I11+1 -> 1242 | I12: =H12+72 -> 1314 | J12: =AVERAGE($D$513:$D$585) -> 15.704918
A13: 12 | B13: 0 | C13: =A13+730 -> 742 | D13: =$D$2 -> 15.704918 | G13: Decline | H13: =I12+1 -> 1315 | I13: =H13+72 -> 1387 | J13: =AVERAGE($D$586:$D$658) -> 15.704918
A14: 13 | B14: 0 | C14: =A14+730 -> 743 | D14: =$D$2 -> 15.704918 | G14: 2nd Trough | H14: =I13+1 -> 1388 | I14: =H14+41 -> 1429 | J14: =AVERAGE($D$659:$D$700) -> 15.704918
A15: 14 | B15: 0 | C15: =A15+730 -> 744 | D15: =$D$2 -> 15.704918 | G15: From day 1430 | H15: =I14+1 -> 1430 | I15: =H15+30 -> 1460 | J15: =AVERAGE($E$701:$E$731) -> 7.852459
A16: 15 | B16: 0 | C16: =A16+730 -> 745 | D16: =$D$2 -> 15.704918
A17: 16 | B17: 0 | C17: =A17+730 -> 746 | D17: =$D$2 -> 15.704918
A18: 17 | B18: 0 | C18: =A18+730 -> 747 | D18: =$D$2 -> 15.704918
A19: 18 | B19: 0 | C19: =A19+730 -> 748 | D19: =$D$2 -> 15.704918
A20: 19 | B20: 0 | C20: =A20+730 -> 749 | D20: =$D$2 -> 15.704918
A21: 20 | B21: 0 | C21: =A21+730 -> 750 | D21: =$D$2 -> 15.704918
A22: 21 | B22: 0 | C22: =A22+730 -> 751 | D22: =$D$2 -> 15.704918
A23: 22 | B23: 0 | C23: =A23+730 -> 752 | D23: =$D$2 -> 15.704918
A24: 23 | B24: 0 | C24: =A24+730 -> 753 | D24: =$D$2 -> 15.704918
A25: 24 | B25: 0 | C25: =A25+730 -> 754 | D25: =$D$2 -> 15.704918
A26: 25 | B26: 0 | C26: =A26+730 -> 755 | D26: =$D$2 -> 15.704918
A27: 26 | B27: 0 | C27: =A27+730 -> 756 | D27: =$D$2 -> 15.704918
... A700: 699 | B700: 0 | C700: =A700+730 -> 1429 | D700: =$D$2 -> 15.704918
A701: 700 | B701: 1 | C701: =A701+730 -> 1430 | D701: =$D$2 -> 15.704918 | E701: =D701*(1460-C701)/30 -> 15.704918
A702: 701 | B702: 26 | C702: =A702+730 -> 1431 | D702: =$D$2 -> 15.704918 | E702: =D702*(1460-C702)/30 -> 15.181421
A703: 702 | B703: 4 | C703: =A703+730 -> 1432 | D703: =$D$2 -> 15.704918 | E703: =D703*(1460-C703)/30 -> 14.657923
A704: 703 | B704: 35 | C704: =A704+730 -> 1433 | D704: =$D$2 -> 15.704918 | E704: =D704*(1460-C704)/30 -> 14.134426
A705: 704 | B705: 6 | C705: =A705+730 -> 1434 | D705: =$D$2 -> 15.704918 | E705: =D705*(1460-C705)/30 -> 13.610929
A706: 705 | B706: 6 | C706: =A706+730 -> 1435 | D706: =$D$2 -> 15.704918 | E706: =D706*(1460-C706)/30 -> 13.087432
A707: 706 | B707: 4 | C707: =A707+730 -> 1436 | D707: =$D$2 -> 15.704918 | E707: =D707*(1460-C707)/30 -> 12.563934
A708: 707 | B708: 29 | C708: =A708+730 -> 1437 | D708: =$D$2 -> 15.704918 | E708: =D708*(1460-C708)/30 -> 12.040437
A709: 708 | B709: 32 | C709: =A709+730 -> 1438 | D709: =$D$2 -> 15.704918 | E709: =D709*(1460-C709)/30 -> 11.51694
A710: 709 | B710: 16 | C710: =A710+730 -> 1439 | D710: =$D$2 -> 15.704918 | E710: =D710*(1460-C710)/30 -> 10.993443
A711: 710 | B711: 27 | C711: =A711+730 -> 1440 | D711: =$D$2 -> 15.704918 | E711: =D711*(1460-C711)/30 -> 10.469945
A712: 711 | B712: 0 | C712: =A712+730 -> 1441 | D712: =$D$2 -> 15.704918 | E712: =D712*(1460-C712)/30 -> 9.9464481
... A731: 730 | B731: 3 | C731: =A731+730 -> 1460 | D731: =$D$2 -> 15.704918 | E731: =D731*(1460-C731)/30 -> 0

Sheet Entworpe
A1: day | B1: Entworpe | C1: forecast - day | D1: forecast - inter-arrival time model | E1: from day 1430 | H1: Fixed order quantity (Q, R) policy: order exactly 250 drums when internal inventory hits reorder point
A2: 1 | B2: 0 | C2: =A2+730 -> 731 | D2: =$I$8 -> 12.5 | H2: Timing is random >> Maintain 250-drum standing buffer in Calopeia warehouse at all times.
A3: 2 | B3: 0 | C3: =A3+730 -> 732 | D3: =$I$8 -> 12.5 | H3: Demand started day 640, stable by day 670 >> use only day 670 - 730 for our forecast
A4: 3 | B4: 0 | C4: =A4+730 -> 733 | D4: =$I$8 -> 12.5
A5: 4 | B5: 0 | C5: =A5+730 -> 734 | D5: =$I$8 -> 12.5 | H5: number of days | I5: 60
A6: 5 | B6: 0 | C6: =A6+730 -> 735 | D6: =$I$8 -> 12.5 | H6: total number of orders | I6: 3
A7: 6 | B7: 0 | C7: =A7+730 -> 736 | D7: =$I$8 -> 12.5 | H7: average inter-arrival time | I7: =I5/I6 -> 20
A8: 7 | B8: 0 | C8: =A8+730 -> 737 | D8: =$I$8 -> 12.5 | H8: underlying daily consumption rate | I8: =250/I7 -> 12.5
A9: 8 | B9: 0 | C9: =A9+730 -> 738 | D9: =$I$8 -> 12.5
A10: 9 | B10: 0 | C10: =A10+730 -> 739 | D10: =$I$8 -> 12.5 | I10: From | J10: To | K10: Forecast | L10: Orders/month
A11: 10 | B11: 0 | C11: =A11+730 -> 740 | D11: =$I$8 -> 12.5 | H11: 1st Trough | I11: =731 -> 731 | J11: =I11+72 -> 803 | K11: =AVERAGE($D$2:$D$74) -> 12.5 | L11: =30/(250/K11) -> 1.5
A12: 11 | B12: 0 | C12: =A12+730 -> 741 | D12: =$I$8 -> 12.5 | H12: Ramp up | I12: =J11+1 -> 804 | J12: =I12+72 -> 876 | K12: =AVERAGE($D$75:$D$147) -> 12.5 | L12: =30/(250/K12) -> 1.5
A13: 12 | B13: 0 | C13: =A13+730 -> 742 | D13: =$I$8 -> 12.5 | H13: Peak | I13: =J12+1 -> 877 | J13: =I13+72 -> 949 | K13: =AVERAGE($D$148:$D$220) -> 12.5 | L13: =30/(250/K13) -> 1.5
A14: 13 | B14: 0 | C14: =A14+730 -> 743 | D14: =$I$8 -> 12.5 | H14: Decline | I14: =J13+1 -> 950 | J14: =I14+72 -> 1022 | K14: =AVERAGE($D$221:$D$293) -> 12.5 | L14: =30/(250/K14) -> 1.5
A15: 14 | B15: 0 | C15: =A15+730 -> 744 | D15: =$I$8 -> 12.5 | H15: 2nd Trough | I15: =J14+1 -> 1023 | J15: =I15+72 -> 1095 | K15: =AVERAGE($D$294:$D$366) -> 12.5 | L15: =30/(250/K15) -> 1.5
A16: 15 | B16: 0 | C16: =A16+730 -> 745 | D16: =$I$8 -> 12.5 | H16: 1st Trough | I16: =J15+1 -> 1096 | J16: =I16+72 -> 1168 | K16: =AVERAGE($D$367:$D$439) -> 12.5 | L16: =30/(250/K16) -> 1.5
A17: 16 | B17: 0 | C17: =A17+730 -> 746 | D17: =$I$8 -> 12.5 | H17: Ramp up | I17: =J16+1 -> 1169 | J17: =I17+72 -> 1241 | K17: =AVERAGE($D$440:$D$512) -> 12.5 | L17: =30/(250/K17) -> 1.5
A18: 17 | B18: 0 | C18: =A18+730 -> 747 | D18: =$I$8 -> 12.5 | H18: Peak | I18: =J17+1 -> 1242 | J18: =I18+72 -> 1314 | K18: =AVERAGE($D$513:$D$585) -> 12.5 | L18: =30/(250/K18) -> 1.5
A19: 18 | B19: 0 | C19: =A19+730 -> 748 | D19: =$I$8 -> 12.5 | H19: Decline | I19: =J18+1 -> 1315 | J19: =I19+72 -> 1387 | K19: =AVERAGE($D$586:$D$658) -> 12.5 | L19: =30/(250/K19) -> 1.5
A20: 19 | B20: 0 | C20: =A20+730 -> 749 | D20: =$I$8 -> 12.5 | H20: 2nd Trough | I20: =J19+1 -> 1388 | J20: =I20+41 -> 1429 | K20: =AVERAGE($D$659:$D$700) -> 12.5 | L20: =30/(250/K20) -> 1.5
A21: 20 | B21: 0 | C21: =A21+730 -> 750 | D21: =$I$8 -> 12.5 | H21: From day 1430 | I21: =J20+1 -> 1430 | J21: =I21+30 -> 1460 | K21: =AVERAGE($E$701:$E$731) -> 6.25 | L21: =30/(250/K21) -> 0.75
A22: 21 | B22: 0 | C22: =A22+730 -> 751 | D22: =$I$8 -> 12.5
A23: 22 | B23: 0 | C23: =A23+730 -> 752 | D23: =$I$8 -> 12.5
A24: 23 | B24: 0 | C24: =A24+730 -> 753 | D24: =$I$8 -> 12.5
A25: 24 | B25: 0 | C25: =A25+730 -> 754 | D25: =$I$8 -> 12.5
A26: 25 | B26: 0 | C26: =A26+730 -> 755 | D26: =$I$8 -> 12.5
A27: 26 | B27: 0 | C27: =A27+730 -> 756 | D27: =$I$8 -> 12.5
A28: 27 | B28: 0 | C28: =A28+730 -> 757 | D28: =$I$8 -> 12.5
A29: 28 | B29: 0 | C29: =A29+730 -> 758 | D29: =$I$8 -> 12.5
A30: 29 | B30: 0 | C30: =A30+730 -> 759 | D30: =$I$8 -> 12.5
A31: 30 | B31: 0 | C31: =A31+730 -> 760 | D31: =$I$8 -> 12.5
A32: 31 | B32: 0 | C32: =A32+730 -> 761 | D32: =$I$8 -> 12.5
A33: 32 | B33: 0 | C33: =A33+730 -> 762 | D33: =$I$8 -> 12.5
... A700: 699 | B700: 0 | C700: =A700+730 -> 1429 | D700: =$I$8 -> 12.5
A701: 700 | B701: 250 | C701: =A701+730 -> 1430 | D701: =$I$8 -> 12.5 | E701: =D701*(1460-C701)/30 -> 12.5
A702: 701 | B702: 0 | C702: =A702+730 -> 1431 | D702: =$I$8 -> 12.5 | E702: =D702*(1460-C702)/30 -> 12.083333
A703: 702 | B703: 0 | C703: =A703+730 -> 1432 | D703: =$I$8 -> 12.5 | E703: =D703*(1460-C703)/30 -> 11.666667
A704: 703 | B704: 0 | C704: =A704+730 -> 1433 | D704: =$I$8 -> 12.5 | E704: =D704*(1460-C704)/30 -> 11.25
A705: 704 | B705: 0 | C705: =A705+730 -> 1434 | D705: =$I$8 -> 12.5 | E705: =D705*(1460-C705)/30 -> 10.833333
A706: 705 | B706: 0 | C706: =A706+730 -> 1435 | D706: =$I$8 -> 12.5 | E706: =D706*(1460-C706)/30 -> 10.416667
A707: 706 | B707: 0 | C707: =A707+730 -> 1436 | D707: =$I$8 -> 12.5 | E707: =D707*(1460-C707)/30 -> 10
A708: 707 | B708: 0 | C708: =A708+730 -> 1437 | D708: =$I$8 -> 12.5 | E708: =D708*(1460-C708)/30 -> 9.5833333
A709: 708 | B709: 0 | C709: =A709+730 -> 1438 | D709: =$I$8 -> 12.5 | E709: =D709*(1460-C709)/30 -> 9.1666667
A710: 709 | B710: 0 | C710: =A710+730 -> 1439 | D710: =$I$8 -> 12.5 | E710: =D710*(1460-C710)/30 -> 8.75
A711: 710 | B711: 0 | C711: =A711+730 -> 1440 | D711: =$I$8 -> 12.5 | E711: =D711*(1460-C711)/30 -> 8.3333333
A712: 711 | B712: 0 | C712: =A712+730 -> 1441 | D712: =$I$8 -> 12.5 | E712: =D712*(1460-C712)/30 -> 7.9166667
... A731: 730 | B731: 0 | C731: =A731+730 -> 1460 | D731: =$I$8 -> 12.5 | E731: =D731*(1460-C731)/30 -> 0
